{
  "team": "Houston Cougars",
  "slug": "houston",
  "url_param": "Houston",
  "conference": "big12",
  "source_url": "https://www.puntandrally.com/teamprofile.php?team=Houston",
  "last_scraped": "2026-04-05",
  "agent_notes": "",
  "known_injuries": [],
  "position_battles": [],
  "search_keywords": [
    "Houston Cougars",
    "Willie Fritz",
    "Anthony Boswell",
    "Makhi Hughes",
    "Shadre Hurst",
    "Amare Thomas",
    "Jordan Allen",
    "Will James",
    "Patrick Overmyer",
    "Drew Terrill",
    "Conner Weigman"
  ],
  "youtube_channels": [],
  "beat_writers": [],
  "team_subreddit": "",
  "sentiment": "",
  "sentiment_score": null,
  "last_research_run": null,
  "twitter_handle": "@UHCougarFB",
  "team_display_name": "Houston Cougars",
  "head_coach": "Willie Fritz",
  "coach_years": "3rd year",
  "coach_record": "14-11",
  "vegas_win_total": "7.5",
  "projected_record": "8-4",
  "projected_record_rank": 28,
  "sos_rank": 63,
  "power_rank": 27,
  "sp_plus_rank": 36,
  "record_prediction": "8-4",
  "record_prediction_rank": 28,
  "coaching_staff_rank": 45,
  "last_season_record": "10-3",
  "last_season_conf_record": "",
  "last_season_ats": "9-4-0",
  "last_season_totals": "8-5",
  "momentum_control_rank": 49,
  "game_control_rank": 51,
  "one_score_games": "6-1",
  "one_score_games_under_coach": "8-2",
  "performance_rank": 46,
  "special_teams_rank": 83,
  "returning_production_pct": 66,
  "returning_production_rank": 53,
  "starting_qb_note": "",
  "returning_offense_pct": 85,
  "returning_offense_rank": 26,
  "returning_defense_pct": 61,
  "returning_defense_rank": 76,
  "returning_starters": 11,
  "returning_starters_off": 5,
  "returning_starters_def": 6,
  "five_year_profile": "Improving Below Avg P4",
  "profile_2026": "Up to Average P4",
  "talent_rank": 54,
  "blue_chip_pct": 6,
  "blue_chip_rank": 52,
  "offense_talent_rank": 58,
  "defense_talent_rank": 47,
  "portal_class_rank": 50,
  "portal_class_count": 19,
  "portal_class_avg": 86,
  "recruiting_class_rank": 32,
  "four_yr_class_rank": 45,
  "talent_profile": "Consistent Average P4",
  "offensive_coordinator": "Slade Nagle",
  "offensive_coordinator_rank": 115,
  "defensive_coordinator": "Austin Armstrong",
  "defensive_coordinator_rank": 36,
  "four_yr_record": "18-19",
  "eight_yr_record": "45-39",
  "avg_wins_under_coach": 7.0,
  "schedule_tiers": {
    "elite": 1,
    "good": 3,
    "avg": 5,
    "bad": 2,
    "poor": 0
  },
  "top_portal_additions": [
    {
      "name": "Anthony Boswell",
      "position": "IOL",
      "stars": 3,
      "rating": 0.88
    },
    {
      "name": "Makhi Hughes",
      "position": "RB",
      "stars": 3,
      "rating": 0.88
    },
    {
      "name": "Javion White",
      "position": "S",
      "stars": 3,
      "rating": 0.88
    },
    {
      "name": "Trent Walker",
      "position": "WR",
      "stars": 3,
      "rating": 0.87
    },
    {
      "name": "Shadre Hurst",
      "position": "IOL",
      "stars": 3,
      "rating": 0.87
    },
    {
      "name": "Ejiroghene Egodogbare",
      "position": "DL",
      "stars": 3,
      "rating": 0.87
    },
    {
      "name": "Ashton Porter",
      "position": "DL",
      "stars": 3,
      "rating": 0.87
    },
    {
      "name": "Jalen Mayo",
      "position": "CB",
      "stars": 3,
      "rating": 0.87
    }
  ],
  "top_performers": [
    {
      "name": "Shadre Hurst",
      "position": "G",
      "stat": "B+ Block Grade (* TR)"
    },
    {
      "name": "Amare Thomas",
      "position": "WR",
      "stat": "966 Yds, 12 TD"
    },
    {
      "name": "Jordan Allen",
      "position": "S",
      "stat": "0 Int, 2 Pd"
    },
    {
      "name": "Will James",
      "position": "CB",
      "stat": "3 Int, 5 Pd"
    },
    {
      "name": "Anthony Boswell",
      "position": "C",
      "stat": "B Block Grade (* TR)"
    },
    {
      "name": "Patrick Overmyer",
      "position": "TE",
      "stat": "344 Yds, 5 TD(* TR)"
    },
    {
      "name": "Drew Terrill",
      "position": "T",
      "stat": "B Block Grade (* TR)"
    },
    {
      "name": "Conner Weigman",
      "position": "QB",
      "stat": "2705 Yds, 25 TD"
    }
  ],
  "top_recruits": [
    {
      "name": "Keisean Henderson",
      "position": "QB",
      "stars": 5,
      "rating": 1.0
    },
    {
      "name": "John Hebert",
      "position": "RB",
      "stars": 4,
      "rating": 0.9
    },
    {
      "name": "Jaivion Martin",
      "position": "TE",
      "stars": 3,
      "rating": 0.89
    },
    {
      "name": "Kaleb Walker",
      "position": "EDGE",
      "stars": 3,
      "rating": 0.88
    },
    {
      "name": "Keavon Roberts",
      "position": "WR",
      "stars": 3,
      "rating": 0.88
    },
    {
      "name": "Bryson Castile",
      "position": "LB",
      "stars": 3,
      "rating": 0.88
    },
    {
      "name": "Jeremiah Bushnell",
      "position": "WR",
      "stars": 3,
      "rating": 0.87
    }
  ],
  "offense_power_rank": 24,
  "defense_power_rank": 33,
  "off_momentum_control_rank": 23,
  "off_game_control_rank": 47,
  "def_momentum_control_rank": null,
  "def_game_control_rank": 61,
  "offense_profile": "",
  "scoring_overall_margin": 6.3,
  "scoring_home_margin": 1.5,
  "scoring_road_margin": 11.5,
  "net_efficiency_rank": 64,
  "offense_ppd_rank": 44,
  "defense_ppd_rank": 39,
  "offense_ppp_rank": 80,
  "defense_ppp_rank": 42,
  "record_2025": "10-3",
  "record_2024": "4-8",
  "team_notes": [
    "(4/2) WR Amare Thomas rated top 10 in CFB via PFF",
    "(4/2) OG Hurst and OC Boswell both PFF top 10 OL",
    "(3/17) LBs are loaded with exp, 6 guys. Should be good",
    "(3/17) QB Weigman good, mobile. Henderson huge croot",
    "(3/17) RB big ? really need Hughes (OU) or depth to hit",
    "(3/17) OL need 3 G6 risers to hit, but very exp'd, promising",
    "(3/17) DL very inexp'd, lacks big options on paper. Big ?",
    "(3/17) DBs look good, CB duo good, Saf has good options",
    "(2/4) WR duo of Thomas/Walker really good. Have depth",
    "(2/4) Pass rush a big concern on paper, v low grades"
  ],
  "injury_notes": [],
  "staff_schedule_notes": [
    "(2/17) Vibes: Great, HC Fritz cookin here, high hopes",
    "(2/6) 247 has Hou portal class #46, On3 top ten?",
    "(2/4) HC Fritz great job 10 wins in year 2. Big jump",
    "(2/4) OC Nagle has a lot to prove this year"
  ],
  "recruiting_class_2026_points": "219",
  "recruiting_class_2026_rank": 32,
  "avg_recruiting_rank": 48,
  "four_year_class_rank": 45,
  "recruiting_profile": "Consistent Average P4",
  "full_roster": [
    {
      "name": "Conner Weigman",
      "jersey": "1",
      "class": "SR",
      "position_group": "Quarterbacks",
      "height_weight": "6'3\"/210",
      "snaps": 356,
      "snap_pct": 65.0,
      "rating": 0.91,
      "origin": ""
    },
    {
      "name": "Luke Carney",
      "jersey": "17",
      "class": "FR",
      "position_group": "Quarterbacks",
      "height_weight": "6'2\"/205",
      "snaps": 7,
      "snap_pct": 71.0,
      "rating": 0.84,
      "origin": ""
    },
    {
      "name": "Keisean Henderson",
      "jersey": "5",
      "class": "FR",
      "position_group": "Quarterbacks",
      "height_weight": "6'5\"/195",
      "snaps": null,
      "snap_pct": null,
      "rating": null,
      "origin": ""
    },
    {
      "name": "DJ Butler",
      "jersey": "25",
      "class": "JR",
      "position_group": "Running Backs",
      "height_weight": "6'0\"/190",
      "snaps": 186,
      "snap_pct": 17.0,
      "rating": 0.86,
      "origin": ""
    },
    {
      "name": "Makhi Hughes",
      "jersey": "21",
      "class": "SR",
      "position_group": "Running Backs",
      "height_weight": "6'0\"/210",
      "snaps": 42,
      "snap_pct": 4.0,
      "rating": 0.88,
      "origin": ""
    },
    {
      "name": "Zane Smith",
      "jersey": "37",
      "class": "SO",
      "position_group": "Running Backs",
      "height_weight": "5'9\"/235",
      "snaps": 5,
      "snap_pct": 0.0,
      "rating": null,
      "origin": "NA"
    },
    {
      "name": "Re'Shaun Sanford II",
      "jersey": "6",
      "class": "SO",
      "position_group": "Running Backs",
      "height_weight": "5'9\"/190",
      "snaps": 4,
      "snap_pct": 0.0,
      "rating": 0.85,
      "origin": ""
    },
    {
      "name": "Aaron Davis",
      "jersey": "38",
      "class": "SO",
      "position_group": "Running Backs",
      "height_weight": "5'11\"/180",
      "snaps": 1,
      "snap_pct": 0.0,
      "rating": null,
      "origin": "NA"
    },
    {
      "name": "John Hebert",
      "jersey": "00",
      "class": "FR",
      "position_group": "Running Backs",
      "height_weight": "5'10\"/185",
      "snaps": null,
      "snap_pct": null,
      "rating": null,
      "origin": ""
    },
    {
      "name": "Amare Thomas",
      "jersey": "00",
      "class": "SR",
      "position_group": "Wide Receivers",
      "height_weight": "6'0\"/205",
      "snaps": 831,
      "snap_pct": 49.0,
      "rating": 0.86,
      "origin": ""
    },
    {
      "name": "Trent Walker",
      "jersey": "4",
      "class": "SR",
      "position_group": "Wide Receivers",
      "height_weight": "6'2\"/195",
      "snaps": 731,
      "snap_pct": 43.0,
      "rating": 0.87,
      "origin": ""
    },
    {
      "name": "Koby Young",
      "jersey": "18",
      "class": "SO",
      "position_group": "Wide Receivers",
      "height_weight": "6'0\"/180",
      "snaps": 590,
      "snap_pct": 35.0,
      "rating": 0.89,
      "origin": ""
    },
    {
      "name": "Harvey Broussard III",
      "jersey": "3",
      "class": "SR",
      "position_group": "Wide Receivers",
      "height_weight": "6'3\"/185",
      "snaps": 471,
      "snap_pct": 28.0,
      "rating": 0.84,
      "origin": ""
    },
    {
      "name": "Jaquise Martin",
      "jersey": "80",
      "class": "SO",
      "position_group": "Wide Receivers",
      "height_weight": "5'10\"/180",
      "snaps": 123,
      "snap_pct": 7.0,
      "rating": 0.86,
      "origin": ""
    },
    {
      "name": "Muizz Tounkara",
      "jersey": "14",
      "class": "SO",
      "position_group": "Wide Receivers",
      "height_weight": "6'3\"/210",
      "snaps": 90,
      "snap_pct": 5.0,
      "rating": 0.86,
      "origin": ""
    },
    {
      "name": "Tyson Turner",
      "jersey": "18",
      "class": "SO",
      "position_group": "Wide Receivers",
      "height_weight": "6'2\"/215",
      "snaps": 43,
      "snap_pct": 3.0,
      "rating": 0.85,
      "origin": ""
    },
    {
      "name": "JayShon Ridgle",
      "jersey": "16",
      "class": "JR",
      "position_group": "Wide Receivers",
      "height_weight": "6'0\"/197",
      "snaps": 1,
      "snap_pct": 0.0,
      "rating": 0.88,
      "origin": ""
    },
    {
      "name": "Keavon Roberts",
      "jersey": "83",
      "class": "FR",
      "position_group": "Wide Receivers",
      "height_weight": "6'5\"/185",
      "snaps": null,
      "snap_pct": null,
      "rating": 0.88,
      "origin": ""
    },
    {
      "name": "Jeremiah Bushnell",
      "jersey": "81",
      "class": "FR",
      "position_group": "Wide Receivers",
      "height_weight": "6'1\"/195",
      "snaps": null,
      "snap_pct": null,
      "rating": 0.87,
      "origin": ""
    },
    {
      "name": "Patrick Overmyer",
      "jersey": "9",
      "class": "JR",
      "position_group": "Tight Ends",
      "height_weight": "6'5\"/230",
      "snaps": 532,
      "snap_pct": 29.0,
      "rating": 0.85,
      "origin": ""
    },
    {
      "name": "Luke McGary",
      "jersey": "87",
      "class": "SR",
      "position_group": "Tight Ends",
      "height_weight": "6'4\"/250",
      "snaps": 203,
      "snap_pct": 11.0,
      "rating": 0.88,
      "origin": ""
    },
    {
      "name": "Kaleb Thomas",
      "jersey": "35",
      "class": "SO",
      "position_group": "Tight Ends",
      "height_weight": "6'4\"/250",
      "snaps": 138,
      "snap_pct": 8.0,
      "rating": 0.85,
      "origin": ""
    },
    {
      "name": "T. Frederick Jr",
      "jersey": "85",
      "class": "JR",
      "position_group": "Tight Ends",
      "height_weight": "6'3\"/240",
      "snaps": 74,
      "snap_pct": 4.0,
      "rating": 0.87,
      "origin": ""
    },
    {
      "name": "Wyatt Herbel",
      "jersey": "86",
      "class": "SO",
      "position_group": "Tight Ends",
      "height_weight": "6'3\"/220",
      "snaps": 8,
      "snap_pct": 0.0,
      "rating": 0.86,
      "origin": ""
    },
    {
      "name": "Jaivion Martin",
      "jersey": "89",
      "class": "FR",
      "position_group": "Tight Ends",
      "height_weight": "6'4\"/250",
      "snaps": null,
      "snap_pct": null,
      "rating": 0.89,
      "origin": ""
    },
    {
      "name": "Jacory Thurman",
      "jersey": "88",
      "class": "SO",
      "position_group": "Tight Ends",
      "height_weight": "6'4\"/240",
      "snaps": null,
      "snap_pct": null,
      "rating": 0.86,
      "origin": ""
    },
    {
      "name": "Alvin Ebosele",
      "jersey": "79",
      "class": "SR",
      "position_group": "Offensive Line",
      "height_weight": "6'6\"/312",
      "snaps": 957,
      "snap_pct": 102.0,
      "rating": 0.85,
      "origin": ""
    },
    {
      "name": "Drew Terrill",
      "jersey": "73",
      "class": "SR",
      "position_group": "Offensive Line",
      "height_weight": "6'6\"/300",
      "snaps": 734,
      "snap_pct": 70.2,
      "rating": 0.85,
      "origin": ""
    },
    {
      "name": "Ronnell McLain",
      "jersey": "53",
      "class": "SO",
      "position_group": "Offensive Line",
      "height_weight": "6'4\"/325",
      "snaps": 10,
      "snap_pct": 1.0,
      "rating": 0.84,
      "origin": ""
    },
    {
      "name": "Troy Pless",
      "jersey": "00",
      "class": "FR",
      "position_group": "Offensive Line",
      "height_weight": "6'5\"/295",
      "snaps": null,
      "snap_pct": null,
      "rating": 0.86,
      "origin": ""
    },
    {
      "name": "Shadre Hurst",
      "jersey": "56",
      "class": "SR",
      "position_group": "Offensive Line",
      "height_weight": "6'2\"/295",
      "snaps": 934,
      "snap_pct": 90.0,
      "rating": 0.87,
      "origin": ""
    },
    {
      "name": "McKenzie Agnello",
      "jersey": "66",
      "class": "SR",
      "position_group": "Offensive Line",
      "height_weight": "6'4\"/314",
      "snaps": 773,
      "snap_pct": 82.0,
      "rating": 0.85,
      "origin": ""
    },
    {
      "name": "Larry Crawford",
      "jersey": "70",
      "class": "JR",
      "position_group": "Offensive Line",
      "height_weight": "6'5\"/300",
      "snaps": 25,
      "snap_pct": 3.0,
      "rating": 0.85,
      "origin": ""
    },
    {
      "name": "Hingano Hautau",
      "jersey": "67",
      "class": "GR",
      "position_group": "Offensive Line",
      "height_weight": "6'6\"/325",
      "snaps": 7,
      "snap_pct": 1.0,
      "rating": 0.84,
      "origin": ""
    },
    {
      "name": "Anthony Boswell",
      "jersey": "52",
      "class": "SO",
      "position_group": "Offensive Line",
      "height_weight": "6'2\"/301",
      "snaps": 819,
      "snap_pct": 78.3,
      "rating": 0.88,
      "origin": ""
    },
    {
      "name": "Demetris Dean II",
      "jersey": "55",
      "class": "SO",
      "position_group": "Offensive Line",
      "height_weight": "6'4\"/300",
      "snaps": null,
      "snap_pct": null,
      "rating": null,
      "origin": ""
    },
    {
      "name": "Aaron Wolford",
      "jersey": "50",
      "class": "FR",
      "position_group": "Offensive Line",
      "height_weight": "6'4\"/310",
      "snaps": null,
      "snap_pct": null,
      "rating": 0.87,
      "origin": ""
    },
    {
      "name": "Rhett Gray",
      "jersey": "54",
      "class": "FR",
      "position_group": "Offensive Line",
      "height_weight": "6'8\"/310",
      "snaps": null,
      "snap_pct": null,
      "rating": 0.87,
      "origin": ""
    },
    {
      "name": "Hayden Wright",
      "jersey": "57",
      "class": "FR",
      "position_group": "Offensive Line",
      "height_weight": "6'5\"/285",
      "snaps": null,
      "snap_pct": null,
      "rating": 0.86,
      "origin": ""
    },
    {
      "name": "Noah Abebe",
      "jersey": "71",
      "class": "FR",
      "position_group": "Offensive Line",
      "height_weight": "6'4\"/300",
      "snaps": null,
      "snap_pct": null,
      "rating": 0.86,
      "origin": ""
    },
    {
      "name": "Sean Terrell",
      "jersey": "68",
      "class": "SO",
      "position_group": "Offensive Line",
      "height_weight": "6'5\"/295",
      "snaps": null,
      "snap_pct": null,
      "rating": 0.85,
      "origin": ""
    },
    {
      "name": "RJ Lee",
      "jersey": "72",
      "class": "SO",
      "position_group": "Offensive Line",
      "height_weight": "6'8\"/335",
      "snaps": null,
      "snap_pct": null,
      "rating": 0.85,
      "origin": ""
    },
    {
      "name": "Ashton Porter",
      "jersey": "9",
      "class": "JR",
      "position_group": "Defensive Line",
      "height_weight": "6'3\"/280",
      "snaps": 244,
      "snap_pct": 20.7,
      "rating": 0.87,
      "origin": ""
    },
    {
      "name": "Chance Bryant",
      "jersey": "45",
      "class": "SO",
      "position_group": "Defensive Line",
      "height_weight": "6'2\"/255",
      "snaps": 88,
      "snap_pct": 8.0,
      "rating": 0.86,
      "origin": ""
    },
    {
      "name": "Darius Washington",
      "jersey": "49",
      "class": "SO",
      "position_group": "Defensive Line",
      "height_weight": "6'6\"/265",
      "snaps": 54,
      "snap_pct": 5.0,
      "rating": 0.87,
      "origin": ""
    },
    {
      "name": "Travis Buhake",
      "jersey": "92",
      "class": "SO",
      "position_group": "Defensive Line",
      "height_weight": "6'2\"/290",
      "snaps": 26,
      "snap_pct": 2.0,
      "rating": 0.89,
      "origin": ""
    },
    {
      "name": "Kaleb Walker",
      "jersey": "00",
      "class": "FR",
      "position_group": "Defensive Line",
      "height_weight": "6'1\"/250",
      "snaps": null,
      "snap_pct": null,
      "rating": 0.88,
      "origin": ""
    },
    {
      "name": "Scott Smith",
      "jersey": "00",
      "class": "FR",
      "position_group": "Defensive Line",
      "height_weight": "6'4\"/230",
      "snaps": null,
      "snap_pct": null,
      "rating": 0.87,
      "origin": ""
    },
    {
      "name": "Khalil Laufau",
      "jersey": "18",
      "class": "SR",
      "position_group": "Defensive Line",
      "height_weight": "6'3\"/290",
      "snaps": 696,
      "snap_pct": 84.0,
      "rating": 0.86,
      "origin": ""
    },
    {
      "name": "De'Marion Thomas",
      "jersey": "90",
      "class": "JR",
      "position_group": "Defensive Line",
      "height_weight": "6'2\"/340",
      "snaps": 148,
      "snap_pct": 16.2,
      "rating": 0.86,
      "origin": ""
    },
    {
      "name": "Myles Parker",
      "jersey": "98",
      "class": "SR",
      "position_group": "Defensive Line",
      "height_weight": "6'1\"/325",
      "snaps": 102,
      "snap_pct": 12.0,
      "rating": 0.83,
      "origin": ""
    },
    {
      "name": "DK Mays",
      "jersey": "47",
      "class": "SO",
      "position_group": "Defensive Line",
      "height_weight": "6'4\"/250",
      "snaps": 2,
      "snap_pct": 0.0,
      "rating": 0.87,
      "origin": ""
    },
    {
      "name": "E. Egodogbare",
      "jersey": "51",
      "class": "SR",
      "position_group": "Defensive Line",
      "height_weight": "6'3\"/310",
      "snaps": null,
      "snap_pct": null,
      "rating": 0.87,
      "origin": ""
    },
    {
      "name": "Carmello Brooks",
      "jersey": "94",
      "class": "SO",
      "position_group": "Defensive Line",
      "height_weight": "6'3\"/275",
      "snaps": null,
      "snap_pct": null,
      "rating": 0.87,
      "origin": ""
    },
    {
      "name": "Xavier Fleming",
      "jersey": "88",
      "class": "FR",
      "position_group": "Defensive Line",
      "height_weight": "6'1\"/305",
      "snaps": null,
      "snap_pct": null,
      "rating": 0.87,
      "origin": ""
    },
    {
      "name": "Quindario Lee",
      "jersey": "99",
      "class": "SR",
      "position_group": "Defensive Line",
      "height_weight": "6'5\"/295",
      "snaps": null,
      "snap_pct": null,
      "rating": 0.87,
      "origin": ""
    },
    {
      "name": "Isaiah Broughton",
      "jersey": "00",
      "class": "FR",
      "position_group": "Defensive Line",
      "height_weight": "6'4\"/300",
      "snaps": null,
      "snap_pct": null,
      "rating": 0.87,
      "origin": ""
    },
    {
      "name": "Eythan Thompson",
      "jersey": "96",
      "class": "SO",
      "position_group": "Defensive Line",
      "height_weight": "6'3\"/330",
      "snaps": null,
      "snap_pct": null,
      "rating": 0.86,
      "origin": ""
    },
    {
      "name": "Sione Fotu",
      "jersey": "12",
      "class": "SR",
      "position_group": "Linebackers",
      "height_weight": "6'0\"/230",
      "snaps": 542,
      "snap_pct": 71.0,
      "rating": 0.85,
      "origin": ""
    },
    {
      "name": "Brandon Mack II",
      "jersey": "4",
      "class": "SR",
      "position_group": "Linebackers",
      "height_weight": "6'4\"/245",
      "snaps": 515,
      "snap_pct": 68.0,
      "rating": 0.83,
      "origin": ""
    },
    {
      "name": "Latreveon McCutchin",
      "jersey": "10",
      "class": "SR",
      "position_group": "Linebackers",
      "height_weight": "6'3\"/245",
      "snaps": 379,
      "snap_pct": 50.0,
      "rating": 0.86,
      "origin": ""
    },
    {
      "name": "Jaden Yates",
      "jersey": "1",
      "class": "SR",
      "position_group": "Linebackers",
      "height_weight": "6'1\"/225",
      "snaps": 371,
      "snap_pct": 49.0,
      "rating": 0.86,
      "origin": ""
    },
    {
      "name": "Carmycah Glass",
      "jersey": "25",
      "class": "JR",
      "position_group": "Linebackers",
      "height_weight": "6'4\"/230",
      "snaps": 351,
      "snap_pct": 46.0,
      "rating": 0.85,
      "origin": ""
    },
    {
      "name": "Miller Malone",
      "jersey": "24",
      "class": "JR",
      "position_group": "Linebackers",
      "height_weight": "6'2\"/220",
      "snaps": 342,
      "snap_pct": 45.0,
      "rating": 0.85,
      "origin": ""
    },
    {
      "name": "Sheldon Rice",
      "jersey": "43",
      "class": "SO",
      "position_group": "Linebackers",
      "height_weight": "6'3\"/250",
      "snaps": 12,
      "snap_pct": 2.0,
      "rating": 0.88,
      "origin": ""
    },
    {
      "name": "Christian Brathwaite",
      "jersey": "17",
      "class": "SO",
      "position_group": "Linebackers",
      "height_weight": "6'2\"/220",
      "snaps": 11,
      "snap_pct": 1.0,
      "rating": 0.88,
      "origin": ""
    },
    {
      "name": "Richmond Ugochukwu",
      "jersey": "30",
      "class": "SO",
      "position_group": "Linebackers",
      "height_weight": "6'2\"/220",
      "snaps": 5,
      "snap_pct": 1.0,
      "rating": 0.87,
      "origin": ""
    },
    {
      "name": "Bryson Castile",
      "jersey": "34",
      "class": "FR",
      "position_group": "Linebackers",
      "height_weight": "6'2\"/210",
      "snaps": null,
      "snap_pct": null,
      "rating": 0.88,
      "origin": ""
    },
    {
      "name": "Tyler Covar",
      "jersey": "35",
      "class": "FR",
      "position_group": "Linebackers",
      "height_weight": "6'2\"/225",
      "snaps": null,
      "snap_pct": null,
      "rating": 0.86,
      "origin": ""
    },
    {
      "name": "Tristan Jackson",
      "jersey": "31",
      "class": "SO",
      "position_group": "Linebackers",
      "height_weight": "6'0\"/215",
      "snaps": null,
      "snap_pct": null,
      "rating": 0.84,
      "origin": ""
    },
    {
      "name": "Jalen Mayo",
      "jersey": "2",
      "class": "SR",
      "position_group": "Linebackers",
      "height_weight": "6'2\"/190",
      "snaps": 737,
      "snap_pct": 44.0,
      "rating": 0.87,
      "origin": ""
    },
    {
      "name": "Will James",
      "jersey": "5",
      "class": "JR",
      "position_group": "Linebackers",
      "height_weight": "6'0\"/185",
      "snaps": 562,
      "snap_pct": 34.0,
      "rating": 0.84,
      "origin": ""
    },
    {
      "name": "Keany Parks",
      "jersey": "19",
      "class": "SR",
      "position_group": "Linebackers",
      "height_weight": "6'1\"/180",
      "snaps": 42,
      "snap_pct": 3.0,
      "rating": 0.85,
      "origin": ""
    },
    {
      "name": "JD Rhym",
      "jersey": "3",
      "class": "SR",
      "position_group": "Linebackers",
      "height_weight": "6'2\"/190",
      "snaps": 10,
      "snap_pct": 1.0,
      "rating": null,
      "origin": "NA"
    },
    {
      "name": "Alvin Williamson Jr",
      "jersey": "23",
      "class": "SO",
      "position_group": "Linebackers",
      "height_weight": "6'0\"/200",
      "snaps": 4,
      "snap_pct": 0.0,
      "rating": 0.85,
      "origin": ""
    },
    {
      "name": "James Henderson III",
      "jersey": "00",
      "class": "FR",
      "position_group": "Linebackers",
      "height_weight": "6'0\"/170",
      "snaps": null,
      "snap_pct": null,
      "rating": 0.87,
      "origin": ""
    },
    {
      "name": "Kentrell Webb",
      "jersey": "8",
      "class": "SR",
      "position_group": "Linebackers",
      "height_weight": "5'11\"/190",
      "snaps": 812,
      "snap_pct": 67.0,
      "rating": 0.87,
      "origin": ""
    },
    {
      "name": "Jordan Allen",
      "jersey": "6",
      "class": "JR",
      "position_group": "Linebackers",
      "height_weight": "5'11\"/200",
      "snaps": 677,
      "snap_pct": 56.0,
      "rating": 0.85,
      "origin": ""
    },
    {
      "name": "Javion White",
      "jersey": "00",
      "class": "JR",
      "position_group": "Linebackers",
      "height_weight": "5'11\"/190",
      "snaps": 654,
      "snap_pct": 54.0,
      "rating": 0.88,
      "origin": ""
    },
    {
      "name": "C.J. Douglas",
      "jersey": "13",
      "class": "SR",
      "position_group": "Linebackers",
      "height_weight": "5'11\"/200",
      "snaps": 77,
      "snap_pct": 6.0,
      "rating": 0.86,
      "origin": ""
    },
    {
      "name": "Johnsley Barbas",
      "jersey": "33",
      "class": "JR",
      "position_group": "Linebackers",
      "height_weight": "5'11\"/190",
      "snaps": null,
      "snap_pct": null,
      "rating": 0.86,
      "origin": ""
    },
    {
      "name": "Jamaal Shaw",
      "jersey": "26",
      "class": "JR",
      "position_group": "Linebackers",
      "height_weight": "6'1\"/200",
      "snaps": null,
      "snap_pct": null,
      "rating": 0.86,
      "origin": ""
    },
    {
      "name": "Paris Melvin",
      "jersey": "14",
      "class": "FR",
      "position_group": "Linebackers",
      "height_weight": "5'11\"/185",
      "snaps": null,
      "snap_pct": null,
      "rating": 0.91,
      "origin": ""
    },
    {
      "name": "Kenzy West",
      "jersey": "28",
      "class": "SO",
      "position_group": "Linebackers",
      "height_weight": "6'0\"/185",
      "snaps": null,
      "snap_pct": null,
      "rating": 0.88,
      "origin": ""
    },
    {
      "name": "Zaylen Cormier",
      "jersey": "82",
      "class": "SO",
      "position_group": "Linebackers",
      "height_weight": "5'11\"/190",
      "snaps": null,
      "snap_pct": null,
      "rating": 0.88,
      "origin": ""
    },
    {
      "name": "Javen Holmes",
      "jersey": "29",
      "class": "FR",
      "position_group": "Linebackers",
      "height_weight": "6'2\"/205",
      "snaps": null,
      "snap_pct": null,
      "rating": 0.87,
      "origin": ""
    },
    {
      "name": "Mudassir Abdullah",
      "jersey": "27",
      "class": "FR",
      "position_group": "Linebackers",
      "height_weight": "6'0\"/175",
      "snaps": null,
      "snap_pct": null,
      "rating": 0.86,
      "origin": ""
    },
    {
      "name": "Zac Yoakam",
      "jersey": "96",
      "class": "SR",
      "position_group": "Kickers",
      "height_weight": "5'8\"/195",
      "snaps": null,
      "snap_pct": null,
      "rating": 0.74,
      "origin": ""
    },
    {
      "name": "Evan Noel",
      "jersey": "94",
      "class": "FR",
      "position_group": "Kickers",
      "height_weight": "6'1\"/165",
      "snaps": null,
      "snap_pct": null,
      "rating": 0.8,
      "origin": ""
    },
    {
      "name": "Liam Dougherty",
      "jersey": "91",
      "class": "JR",
      "position_group": "Punters",
      "height_weight": "6'2\"/205",
      "snaps": null,
      "snap_pct": null,
      "rating": null,
      "origin": "NA"
    }
  ],
  "portal_in": [
    {
      "name": "Anthony Boswell",
      "position": "IOL",
      "school": "Toledo",
      "stars": 3,
      "rating": 88,
      "date": "01-07-26"
    },
    {
      "name": "Makhi Hughes",
      "position": "RB",
      "school": "Oregon",
      "stars": 3,
      "rating": 88,
      "date": "01-04-26"
    },
    {
      "name": "Javion White",
      "position": "S",
      "school": "Tulane",
      "stars": 3,
      "rating": 88,
      "date": "01-13-26"
    },
    {
      "name": "Trent Walker",
      "position": "WR",
      "school": "Oregon State",
      "stars": 3,
      "rating": 87,
      "date": "01-07-26"
    },
    {
      "name": "Shadre Hurst",
      "position": "IOL",
      "school": "Tulane",
      "stars": 3,
      "rating": 87,
      "date": "01-04-26"
    },
    {
      "name": "Ejiroghene Egodogbare",
      "position": "DL",
      "school": "Yale",
      "stars": 3,
      "rating": 87,
      "date": "01-07-26"
    },
    {
      "name": "Ashton Porter",
      "position": "DL",
      "school": "Oregon",
      "stars": 3,
      "rating": 87,
      "date": "01-15-26"
    },
    {
      "name": "Jalen Mayo",
      "position": "CB",
      "school": "Stephen F. Austin",
      "stars": 3,
      "rating": 87,
      "date": "12-31-25"
    },
    {
      "name": "Muizz Tounkara",
      "position": "WR",
      "school": "Florida",
      "stars": 3,
      "rating": 86,
      "date": "01-15-26"
    },
    {
      "name": "Jaden Yates",
      "position": "LB",
      "school": "Ole Miss",
      "stars": 3,
      "rating": 86,
      "date": "01-10-26"
    },
    {
      "name": "De'Marion Thomas",
      "position": "DL",
      "school": "Oklahoma State",
      "stars": 3,
      "rating": 86,
      "date": "01-07-26"
    },
    {
      "name": "Drew Terrill",
      "position": "OT",
      "school": "Miami (OH)",
      "stars": 3,
      "rating": 85,
      "date": "01-04-26"
    },
    {
      "name": "Tyson Turner",
      "position": "WR",
      "school": "Texas Tech",
      "stars": 3,
      "rating": 85,
      "date": "01-10-26"
    },
    {
      "name": "Miller Malone",
      "position": "LB",
      "school": "Western Kentucky",
      "stars": 3,
      "rating": 85,
      "date": "01-09-26"
    },
    {
      "name": "Patrick Overmyer",
      "position": "TE",
      "school": "UTSA",
      "stars": 3,
      "rating": 85,
      "date": "01-07-26"
    },
    {
      "name": "Luke Carney",
      "position": "QB",
      "school": "Syracuse",
      "stars": 3,
      "rating": 84,
      "date": "01-12-26"
    },
    {
      "name": "Evan Noel",
      "position": "K",
      "school": "Florida",
      "stars": 3,
      "rating": 80,
      "date": "01-12-26"
    },
    {
      "name": "Jack Carson-Wentz",
      "position": "LS",
      "school": "Florida A&M",
      "stars": 0,
      "rating": 0,
      "date": "01-22-26"
    },
    {
      "name": "Hayden Wright",
      "position": "OT",
      "school": "Northwestern",
      "stars": 3,
      "rating": 0,
      "date": "01-05-26"
    }
  ],
  "portal_out": [
    {
      "name": "Corey Platt Jr.",
      "position": "LB",
      "school": "Texas Tech",
      "stars": 3,
      "rating": 86,
      "date": "01-12-26"
    },
    {
      "name": "Austin Carlisle",
      "position": "QB",
      "school": "UL Monroe",
      "stars": 3,
      "rating": 86,
      "date": "01-12-26"
    },
    {
      "name": "Demetrius Hunter",
      "position": "IOL",
      "school": "Colorado",
      "stars": 3,
      "rating": 86,
      "date": "01-14-26"
    },
    {
      "name": "Joshua Donald",
      "position": "DL",
      "school": "Louisville",
      "stars": 3,
      "rating": 84,
      "date": "01-15-26"
    },
    {
      "name": "Zion Taylor",
      "position": "EDGE",
      "school": "Sam Houston",
      "stars": 3,
      "rating": 83,
      "date": "01-12-26"
    },
    {
      "name": "Cavan Tuley",
      "position": "EDGE",
      "school": "Missouri",
      "stars": 3,
      "rating": 83,
      "date": "01-12-26"
    },
    {
      "name": "Devan Williams",
      "position": "WR",
      "school": "Lamar Christian School",
      "stars": 3,
      "rating": 0,
      "date": "01-23-26"
    },
    {
      "name": "Reshad Sterling",
      "position": "EDGE",
      "school": "Tulane",
      "stars": 3,
      "rating": 0,
      "date": "01-09-26"
    },
    {
      "name": "Jayden York",
      "position": "TE",
      "school": "TBD",
      "stars": 0,
      "rating": 0,
      "date": "01-12-26"
    },
    {
      "name": "Zavian Tibbs",
      "position": "EDGE",
      "school": "TBD",
      "stars": 0,
      "rating": 0,
      "date": "12-30-25"
    },
    {
      "name": "Zeon Chriss-Gremillion",
      "position": "QB",
      "school": "Tulane",
      "stars": 3,
      "rating": 0,
      "date": "01-07-26"
    },
    {
      "name": "Cayden Bowie",
      "position": "IOL",
      "school": "TBD",
      "stars": 3,
      "rating": 0,
      "date": "01-04-26"
    },
    {
      "name": "David Ndukwe",
      "position": "OT",
      "school": "TBD",
      "stars": 3,
      "rating": 0,
      "date": "01-16-26"
    },
    {
      "name": "Derek Joiner",
      "position": "IOL",
      "school": "Tarleton State",
      "stars": 3,
      "rating": 0,
      "date": "02-04-26"
    },
    {
      "name": "Jesus Machado",
      "position": "LB",
      "school": "Rice",
      "stars": 3,
      "rating": 0,
      "date": "01-12-26"
    }
  ],
  "portal_net": 4,
  "recruiting_class_2026": [
    {
      "name": "Keisean Henderson",
      "position": "QB",
      "stars": 5,
      "rating": 99.9,
      "ranking": 3,
      "height_weight": "6' 3/185",
      "location": "Spring, TX"
    },
    {
      "name": "Paris Melvin Jr.",
      "position": "ATH",
      "stars": 4,
      "rating": 91.12,
      "ranking": 260,
      "height_weight": "5' 11/170",
      "location": "Cypress, TX"
    },
    {
      "name": "John Hebert",
      "position": "RB",
      "stars": 4,
      "rating": 90.36,
      "ranking": 315,
      "height_weight": "5' 10/185",
      "location": "Houston, TX"
    },
    {
      "name": "Jaivion Martin",
      "position": "TE",
      "stars": 3,
      "rating": 88.78,
      "ranking": 496,
      "height_weight": "6' 4/250",
      "location": "Willis, TX"
    },
    {
      "name": "Kaleb Walker",
      "position": "EDGE",
      "stars": 3,
      "rating": 87.67,
      "ranking": 774,
      "height_weight": "6' 1/250",
      "location": "Lindale, TX"
    },
    {
      "name": "Keavon Roberts",
      "position": "WR",
      "stars": 3,
      "rating": 87.67,
      "ranking": 774,
      "height_weight": "6' 4/175",
      "location": "Port Arthur, TX"
    },
    {
      "name": "Bryson Castile",
      "position": "LB",
      "stars": 3,
      "rating": 87.56,
      "ranking": 831,
      "height_weight": "6' 3/195",
      "location": "Arlington, TX"
    },
    {
      "name": "Jeremiah Bushnell",
      "position": "WR",
      "stars": 3,
      "rating": 87.11,
      "ranking": 1009,
      "height_weight": "6' 1/185",
      "location": "Iowa, LA"
    },
    {
      "name": "Scott Smith",
      "position": "EDGE",
      "stars": 3,
      "rating": 87.0,
      "ranking": 867,
      "height_weight": "6' 4/230",
      "location": "Baton Rouge, LA"
    },
    {
      "name": "Isaiah Broughton",
      "position": "DL",
      "stars": 3,
      "rating": 87.0,
      "ranking": 1059,
      "height_weight": "6' 4/300",
      "location": "Houston, TX"
    },
    {
      "name": "Rhett Gray",
      "position": "OT",
      "stars": 3,
      "rating": 86.89,
      "ranking": 1131,
      "height_weight": "6' 7/290",
      "location": "Weatherford, TX"
    },
    {
      "name": "James Henderson III",
      "position": "CB",
      "stars": 3,
      "rating": 86.78,
      "ranking": 1158,
      "height_weight": "6' 0/170",
      "location": "Houston, TX"
    },
    {
      "name": "Xavier Fleming",
      "position": "DL",
      "stars": 3,
      "rating": 86.78,
      "ranking": 1001,
      "height_weight": "6' 0/300",
      "location": "Lewisville, TX"
    },
    {
      "name": "Javen Holmes",
      "position": "S",
      "stars": 3,
      "rating": 86.78,
      "ranking": 1158,
      "height_weight": "6' 1/200",
      "location": "Baton Rouge, LA"
    },
    {
      "name": "Troy Pless",
      "position": "OT",
      "stars": 3,
      "rating": 86.44,
      "ranking": 1320,
      "height_weight": "6' 5/295",
      "location": "Killeen, TX"
    },
    {
      "name": "Noah Abebe",
      "position": "IOL",
      "stars": 3,
      "rating": 86.11,
      "ranking": 1465,
      "height_weight": "6' 4/275",
      "location": "Friendswood, TX"
    },
    {
      "name": "Tyler Covar",
      "position": "LB",
      "stars": 3,
      "rating": 86.0,
      "ranking": 1500,
      "height_weight": "6' 2/215",
      "location": "Magnolia, TX"
    },
    {
      "name": "Mudassir Abdullah",
      "position": "S",
      "stars": 3,
      "rating": 85.67,
      "ranking": 1687,
      "height_weight": "6' 0/165",
      "location": "West Columbia, TX"
    }
  ],
  "schedule_2026": [
    {
      "week": 1,
      "date": "Sat, 9/5",
      "location": "vs",
      "opponent": "Oregon State Beavers",
      "opp_record": "0-0",
      "opp_rank": 106,
      "off_rank": 99,
      "def_rank": 110,
      "favorite": "Houston",
      "line": -17.5,
      "win_pct": 89,
      "proj_w": 0.9,
      "proj_l": 0.1,
      "conference_game": false
    },
    {
      "week": 2,
      "date": "Sat, 9/12",
      "location": "vs",
      "opponent": "Southern Jaguars",
      "opp_record": "0-0",
      "opp_rank": 136,
      "off_rank": 136,
      "def_rank": 136,
      "favorite": "Houston",
      "line": -29.5,
      "win_pct": 99,
      "proj_w": 1.9,
      "proj_l": 0.1,
      "conference_game": false
    },
    {
      "week": 3,
      "date": "Sat, 9/19",
      "location": "at",
      "opponent": "Texas Tech Red Raiders",
      "opp_record": "0-0",
      "opp_rank": 3,
      "off_rank": 3,
      "def_rank": 3,
      "favorite": "Texas Tech",
      "line": 19.0,
      "win_pct": 9,
      "proj_w": 2.0,
      "proj_l": 1.0,
      "conference_game": true
    },
    {
      "week": 4,
      "date": "Sat, 9/26",
      "location": "at",
      "opponent": "Georgia Southern Eagles",
      "opp_record": "0-0",
      "opp_rank": 107,
      "off_rank": 115,
      "def_rank": 81,
      "favorite": "Houston",
      "line": -15.0,
      "win_pct": 85,
      "proj_w": 2.9,
      "proj_l": 1.1,
      "conference_game": false
    },
    {
      "week": 5,
      "date": "Sat, 10/3",
      "location": "vs",
      "opponent": "UCF Knights",
      "opp_record": "0-0",
      "opp_rank": 46,
      "off_rank": 47,
      "def_rank": 50,
      "favorite": "Houston",
      "line": -7.0,
      "win_pct": 70,
      "proj_w": 3.6,
      "proj_l": 1.4,
      "conference_game": true
    },
    {
      "week": 6,
      "date": "Sat, 10/10",
      "location": "at",
      "opponent": "Kansas State Wildcats",
      "opp_record": "0-0",
      "opp_rank": 36,
      "off_rank": 37,
      "def_rank": 37,
      "favorite": "Kansas State",
      "line": 0.5,
      "win_pct": 47,
      "proj_w": 4.1,
      "proj_l": 1.9,
      "conference_game": true
    },
    {
      "week": 7,
      "date": "Sat, 10/17",
      "location": "vs",
      "opponent": "Oklahoma State Cowboys",
      "opp_record": "0-0",
      "opp_rank": 47,
      "off_rank": 25,
      "def_rank": 67,
      "favorite": "Houston",
      "line": -5.5,
      "win_pct": 67,
      "proj_w": 4.8,
      "proj_l": 2.2,
      "conference_game": true
    },
    {
      "week": 8,
      "date": "Sat, 10/24",
      "location": "at",
      "opponent": "Utah Utes",
      "opp_record": "0-0",
      "opp_rank": 30,
      "off_rank": 35,
      "def_rank": 27,
      "favorite": "Utah",
      "line": 2.0,
      "win_pct": 45,
      "proj_w": 5.3,
      "proj_l": 2.7,
      "conference_game": true
    },
    {
      "week": 10,
      "date": "Sat, 11/7",
      "location": "vs",
      "opponent": "Cincinnati Bearcats",
      "opp_record": "0-0",
      "opp_rank": 80,
      "off_rank": 93,
      "def_rank": 63,
      "favorite": "Houston",
      "line": -10.0,
      "win_pct": 77,
      "proj_w": 6.1,
      "proj_l": 2.9,
      "conference_game": true
    },
    {
      "week": 11,
      "date": "Sat, 11/14",
      "location": "at",
      "opponent": "Colorado Buffaloes",
      "opp_record": "0-0",
      "opp_rank": 70,
      "off_rank": 70,
      "def_rank": 72,
      "favorite": "Houston",
      "line": -7.0,
      "win_pct": 70,
      "proj_w": 6.8,
      "proj_l": 3.2,
      "conference_game": true
    },
    {
      "week": 12,
      "date": "Sat, 11/21",
      "location": "at",
      "opponent": "West Virginia Mountaineers",
      "opp_record": "0-0",
      "opp_rank": 62,
      "off_rank": 46,
      "def_rank": 84,
      "favorite": "Houston",
      "line": -6.0,
      "win_pct": 66,
      "proj_w": 7.5,
      "proj_l": 3.5,
      "conference_game": true
    },
    {
      "week": 13,
      "date": "Sat, 11/28",
      "location": "vs",
      "opponent": "Baylor Bears",
      "opp_record": "0-0",
      "opp_rank": 50,
      "off_rank": 59,
      "def_rank": 47,
      "favorite": "Houston",
      "line": -7.0,
      "win_pct": 70,
      "proj_w": 8.2,
      "proj_l": 3.8,
      "conference_game": true
    }
  ],
  "schedule_summary": {
    "total_opp_power": "29",
    "sos_rank": "63",
    "expected_record": null,
    "expected_conf_record": null,
    "p4_g6_opponents": "9 / 2\n",
    "vs_bowl_teams": "0 – 0\n"
  },
  "power_rating_value": 8.31,
  "offense_rating": 19.86,
  "defense_rating": 11.55,
  "power_rank_db": 27,
  "composite_rank": 46,
  "gc_net_raw": 2.58,
  "mc_net_raw": -0.1,
  "composite_score": 64.06,
  "offense_ppa_rank": 102,
  "defense_ppa_rank": 44,
  "offense_success_rank": 74,
  "defense_success_rank": 65,
  "offense_explosiveness_rank": 85,
  "defense_explosiveness_rank": 9,
  "offense_havoc_rank": 36,
  "defense_havoc_rank": 58,
  "offense_ppo_rank": 83,
  "defense_ppo_rank": 94,
  "offense_profile_db": "Balanced (53% pass, 47% run)",
  "scoring_home_ppg": 25.7,
  "scoring_home_games": 6,
  "scoring_road_ppg": 31.0,
  "scoring_road_games": 6,
  "best_players": [
    {
      "player_name": "Shadre Hurst",
      "position": "G",
      "points": 84,
      "statsline": "B+ Block Grade (* TR)"
    },
    {
      "player_name": "Amare Thomas",
      "position": "WR",
      "points": 82,
      "statsline": "966 Yds, 12 TD"
    },
    {
      "player_name": "Jordan Allen",
      "position": "S",
      "points": 80,
      "statsline": "0 Int, 2 Pd"
    },
    {
      "player_name": "Will James",
      "position": "CB",
      "points": 80,
      "statsline": "3 Int, 5 Pd"
    },
    {
      "player_name": "Anthony Boswell",
      "position": "C",
      "points": 80,
      "statsline": "B Block Grade (* TR)"
    },
    {
      "player_name": "Patrick Overmyer",
      "position": "TE",
      "points": 79,
      "statsline": "344 Yds, 5 TD(* TR)"
    },
    {
      "player_name": "Drew Terrill",
      "position": "T",
      "points": 78,
      "statsline": "B Block Grade (* TR)"
    },
    {
      "player_name": "Conner Weigman",
      "position": "QB",
      "points": 77,
      "statsline": "2705 Yds, 25 TD"
    }
  ],
  "previous_head_coach": "Willie Fritz",
  "previous_oc": "Slade Nagle",
  "previous_dc": "Austin Armstrong",
  "db_enriched_at": "2026-04-05"
}