{
  "team": "NC State Wolfpack",
  "slug": "nc-state",
  "url_param": "NC State",
  "conference": "acc",
  "source_url": "https://www.puntandrally.com/teamprofile.php?team=NC%20State",
  "last_scraped": "2026-04-05",
  "agent_notes": "",
  "known_injuries": [],
  "position_battles": [],
  "search_keywords": [
    "NC State Wolfpack",
    "Dave Doeren",
    "Hunter Provience",
    "Raul Aguirre Jr.",
    "Jayden Scott",
    "King Mack",
    "Victor Snow",
    "Asaad Brown Jr.",
    "CJ Bailey",
    "Brian Nelson II",
    "Teague Andersen",
    "Jackson Waller"
  ],
  "youtube_channels": [],
  "beat_writers": [],
  "team_subreddit": "",
  "sentiment": "",
  "sentiment_score": null,
  "last_research_run": null,
  "twitter_handle": "@PackFootball",
  "team_display_name": "NC State Wolfpack",
  "head_coach": "Dave Doeren",
  "coach_years": "14th year",
  "coach_record": "95-70",
  "vegas_win_total": "6.5",
  "projected_record": "8-4",
  "projected_record_rank": 37,
  "sos_rank": 73,
  "power_rank": 35,
  "sp_plus_rank": 48,
  "record_prediction": "8-4",
  "record_prediction_rank": 37,
  "coaching_staff_rank": 73,
  "last_season_record": "8-5",
  "last_season_conf_record": "4-4",
  "last_season_ats": "7-6-0",
  "last_season_totals": "7-6",
  "momentum_control_rank": 91,
  "game_control_rank": 46,
  "one_score_games": "2-1",
  "one_score_games_under_coach": "32-23",
  "performance_rank": 75,
  "special_teams_rank": 91,
  "returning_production_pct": 68,
  "returning_production_rank": 38,
  "starting_qb_note": "",
  "returning_offense_pct": 84,
  "returning_offense_rank": 31,
  "returning_defense_pct": 55,
  "returning_defense_rank": 100,
  "returning_starters": 9,
  "returning_starters_off": 5,
  "returning_starters_def": 4,
  "five_year_profile": "Consistent Below Avg P4",
  "profile_2026": "Remains Below Avg P4",
  "talent_rank": 27,
  "blue_chip_pct": 5,
  "blue_chip_rank": 55,
  "offense_talent_rank": 28,
  "defense_talent_rank": 36,
  "portal_class_rank": 44,
  "portal_class_count": 19,
  "portal_class_avg": 86,
  "recruiting_class_rank": 47,
  "four_yr_class_rank": 39,
  "talent_profile": "Consistent Top 25 Contenders",
  "offensive_coordinator": "Kurt Roper",
  "offensive_coordinator_rank": 43,
  "defensive_coordinator": "D. J. Eliot",
  "defensive_coordinator_rank": 119,
  "four_yr_record": "23-16",
  "eight_yr_record": "52-36",
  "avg_wins_under_coach": 7.31,
  "schedule_tiers": {
    "elite": 0,
    "good": 5,
    "avg": 3,
    "bad": 2,
    "poor": 1
  },
  "top_portal_additions": [
    {
      "name": "Hunter Provience",
      "position": "TE",
      "stars": 3,
      "rating": 0.89
    },
    {
      "name": "Joshisa Trader",
      "position": "WR",
      "stars": 3,
      "rating": 0.88
    },
    {
      "name": "Vander Ploog",
      "position": "TE",
      "stars": 3,
      "rating": 0.87
    },
    {
      "name": "King Mack",
      "position": "S",
      "stars": 3,
      "rating": 0.87
    },
    {
      "name": "Ondre Evans",
      "position": "CB",
      "stars": 3,
      "rating": 0.87
    },
    {
      "name": "Tyran Warren",
      "position": "WR",
      "stars": 3,
      "rating": 0.86
    },
    {
      "name": "Davion Gause",
      "position": "RB",
      "stars": 3,
      "rating": 0.86
    }
  ],
  "top_performers": [
    {
      "name": "Jayden Scott",
      "position": "RB",
      "stat": "595 Yds, 4 TD"
    },
    {
      "name": "King Mack",
      "position": "S",
      "stat": "1 Int, 3 Pd (* TR)"
    },
    {
      "name": "Victor Snow",
      "position": "WR",
      "stat": "815 Yds, 8 TD (* TR)"
    },
    {
      "name": "CJ Bailey",
      "position": "QB",
      "stat": "3105 Yds, 25 TD"
    },
    {
      "name": "Teague Andersen",
      "position": "T",
      "stat": "C+ Block Grade"
    },
    {
      "name": "Brian Nelson II",
      "position": "CB",
      "stat": "0 Int, 6 Pd"
    },
    {
      "name": "Jackson Waller",
      "position": "P",
      "stat": "59 Punts, 41.3 YPP (* TR)"
    }
  ],
  "top_recruits": [
    {
      "name": "Damaad Lewis",
      "position": "DL",
      "stars": 3,
      "rating": 0.89
    },
    {
      "name": "Amiri Acker",
      "position": "WR",
      "stars": 3,
      "rating": 0.88
    },
    {
      "name": "Jordyn Best",
      "position": "CB",
      "stars": 3,
      "rating": 0.88
    },
    {
      "name": "D'Various Surratt",
      "position": "S",
      "stars": 3,
      "rating": 0.88
    },
    {
      "name": "Koby Sarkodie",
      "position": "S",
      "stars": 3,
      "rating": 0.88
    },
    {
      "name": "Ziggy Moore",
      "position": "LB",
      "stars": 3,
      "rating": 0.87
    },
    {
      "name": "Tristen Hill",
      "position": "S",
      "stars": 3,
      "rating": 0.87
    },
    {
      "name": "Chino Aguirre",
      "position": "S",
      "stars": 3,
      "rating": 0.87
    }
  ],
  "offense_power_rank": 38,
  "defense_power_rank": 34,
  "off_momentum_control_rank": 70,
  "off_game_control_rank": 45,
  "def_momentum_control_rank": null,
  "def_game_control_rank": 58,
  "offense_profile": "",
  "scoring_overall_margin": 3.0,
  "scoring_home_margin": 14.3,
  "scoring_road_margin": null,
  "net_efficiency_rank": 54,
  "offense_ppd_rank": 29,
  "defense_ppd_rank": 99,
  "offense_ppp_rank": 28,
  "defense_ppp_rank": 87,
  "record_2025": "8-5",
  "record_2024": "6-7",
  "team_notes": [
    "(2/6) QB Bailey back is big, depth behind him is ?",
    "(2/6) RB Scott (#2 LY) back after good Fr yr, depth ?",
    "(2/6) WR sneaky good portal class of 5, esp Snow (Buf)",
    "(2/6) OL returns 4 w starting exp, 2 portals. Decent",
    "(2/6) DT has some exp, DE/LB has more but not sold",
    "(2/6) DBs have options, CB has more ?, S looks good"
  ],
  "injury_notes": [],
  "staff_schedule_notes": [
    "(2/17) Vibes: Unclear. Good but Doeren era feels stale"
  ],
  "recruiting_class_2026_points": "210",
  "recruiting_class_2026_rank": 47,
  "avg_recruiting_rank": 43,
  "four_year_class_rank": 39,
  "recruiting_profile": "Consistent Top 25 Contenders",
  "full_roster": [
    {
      "name": "CJ Bailey",
      "jersey": "11",
      "class": "JR",
      "position_group": "Quarterbacks",
      "height_weight": "6'6\"/213",
      "snaps": 397,
      "snap_pct": 69.0,
      "rating": 0.89,
      "origin": ""
    },
    {
      "name": "Tad Hudson",
      "jersey": "12",
      "class": "JR",
      "position_group": "Quarterbacks",
      "height_weight": "6'3\"/227",
      "snaps": 254,
      "snap_pct": 55.0,
      "rating": 0.89,
      "origin": ""
    },
    {
      "name": "Will Wilson",
      "jersey": "10",
      "class": "SO",
      "position_group": "Quarterbacks",
      "height_weight": "6'1\"/230",
      "snaps": 5,
      "snap_pct": 60.0,
      "rating": 0.88,
      "origin": ""
    },
    {
      "name": "Jacob Smith",
      "jersey": "14",
      "class": "FR",
      "position_group": "Quarterbacks",
      "height_weight": "6'1\"/211",
      "snaps": null,
      "snap_pct": null,
      "rating": 0.85,
      "origin": ""
    },
    {
      "name": "Hudson Wilharm",
      "jersey": "15",
      "class": "SO",
      "position_group": "Quarterbacks",
      "height_weight": "6'5\"/195",
      "snaps": null,
      "snap_pct": null,
      "rating": 0.74,
      "origin": ""
    },
    {
      "name": "Jayden Scott",
      "jersey": "4",
      "class": "SO",
      "position_group": "Running Backs",
      "height_weight": "5'10\"/214",
      "snaps": 336,
      "snap_pct": 52.0,
      "rating": 0.88,
      "origin": ""
    },
    {
      "name": "Davion Gause",
      "jersey": "7",
      "class": "JR",
      "position_group": "Running Backs",
      "height_weight": "5'11\"/212",
      "snaps": 231,
      "snap_pct": 36.0,
      "rating": 0.86,
      "origin": ""
    },
    {
      "name": "Darius Johnson",
      "jersey": "25",
      "class": "JR",
      "position_group": "Running Backs",
      "height_weight": "5'10\"/205",
      "snaps": 50,
      "snap_pct": 8.0,
      "rating": null,
      "origin": "NA"
    },
    {
      "name": "Deandre Desinor",
      "jersey": "20",
      "class": "FR",
      "position_group": "Running Backs",
      "height_weight": "5'10\"/183",
      "snaps": null,
      "snap_pct": null,
      "rating": 0.89,
      "origin": ""
    },
    {
      "name": "Isiah Jones",
      "jersey": "26",
      "class": "SO",
      "position_group": "Running Backs",
      "height_weight": "5'8\"/200",
      "snaps": null,
      "snap_pct": null,
      "rating": 0.86,
      "origin": ""
    },
    {
      "name": "Dylan McCoy",
      "jersey": "24",
      "class": "FR",
      "position_group": "Running Backs",
      "height_weight": "5'8\"/197",
      "snaps": null,
      "snap_pct": null,
      "rating": 0.86,
      "origin": ""
    },
    {
      "name": "Noah Moss",
      "jersey": "00",
      "class": "FR",
      "position_group": "Running Backs",
      "height_weight": "6'1\"/205",
      "snaps": null,
      "snap_pct": null,
      "rating": 0.86,
      "origin": ""
    },
    {
      "name": "Victor Snow",
      "jersey": "00",
      "class": "SR",
      "position_group": "Wide Receivers",
      "height_weight": "5'8\"/170",
      "snaps": 776,
      "snap_pct": 57.0,
      "rating": 0.86,
      "origin": ""
    },
    {
      "name": "Keenan Jackson",
      "jersey": "8",
      "class": "JR",
      "position_group": "Wide Receivers",
      "height_weight": "6'3\"/202",
      "snaps": 604,
      "snap_pct": 44.0,
      "rating": 0.88,
      "origin": ""
    },
    {
      "name": "Tyran Warren",
      "jersey": "13",
      "class": "SR",
      "position_group": "Wide Receivers",
      "height_weight": "6'3\"/180",
      "snaps": 552,
      "snap_pct": 40.0,
      "rating": 0.86,
      "origin": ""
    },
    {
      "name": "Davion Dozier",
      "jersey": "16",
      "class": "JR",
      "position_group": "Wide Receivers",
      "height_weight": "6'3\"/195",
      "snaps": 499,
      "snap_pct": 37.0,
      "rating": 0.85,
      "origin": ""
    },
    {
      "name": "Teddy Hoffmann",
      "jersey": "12",
      "class": "SO",
      "position_group": "Wide Receivers",
      "height_weight": "6'1\"/181",
      "snaps": 272,
      "snap_pct": 20.0,
      "rating": 0.86,
      "origin": ""
    },
    {
      "name": "Joshisa Trader",
      "jersey": "2",
      "class": "JR",
      "position_group": "Wide Receivers",
      "height_weight": "6'1\"/190",
      "snaps": 223,
      "snap_pct": 16.0,
      "rating": 0.88,
      "origin": ""
    },
    {
      "name": "Ethan Dowdy",
      "jersey": "80",
      "class": "JR",
      "position_group": "Wide Receivers",
      "height_weight": "6'2\"/197",
      "snaps": 32,
      "snap_pct": 2.0,
      "rating": null,
      "origin": "NA"
    },
    {
      "name": "Ashton Locklear",
      "jersey": "27",
      "class": "SR",
      "position_group": "Wide Receivers",
      "height_weight": "6'1\"/188",
      "snaps": 28,
      "snap_pct": 2.0,
      "rating": null,
      "origin": "NA"
    },
    {
      "name": "Chance Robinson",
      "jersey": "82",
      "class": "SO",
      "position_group": "Wide Receivers",
      "height_weight": "6'2\"/205",
      "snaps": 12,
      "snap_pct": 1.0,
      "rating": 0.86,
      "origin": ""
    },
    {
      "name": "Addison Carlson",
      "jersey": "37",
      "class": "SO",
      "position_group": "Wide Receivers",
      "height_weight": "5'11\"/186",
      "snaps": 4,
      "snap_pct": 0.0,
      "rating": null,
      "origin": "NA"
    },
    {
      "name": "Je'rel Bolder",
      "jersey": "21",
      "class": "FR",
      "position_group": "Wide Receivers",
      "height_weight": "6'0\"/212",
      "snaps": 3,
      "snap_pct": 0.0,
      "rating": 0.91,
      "origin": ""
    },
    {
      "name": "Jonathan Paylor",
      "jersey": "14",
      "class": "SO",
      "position_group": "Wide Receivers",
      "height_weight": "5'9\"/182",
      "snaps": null,
      "snap_pct": null,
      "rating": 0.95,
      "origin": ""
    },
    {
      "name": "Amiri Acker",
      "jersey": "83",
      "class": "FR",
      "position_group": "Wide Receivers",
      "height_weight": "6'2\"/190",
      "snaps": null,
      "snap_pct": null,
      "rating": 0.88,
      "origin": ""
    },
    {
      "name": "Jai Richburg",
      "jersey": "89",
      "class": "FR",
      "position_group": "Wide Receivers",
      "height_weight": "6'2\"/190",
      "snaps": null,
      "snap_pct": null,
      "rating": 0.87,
      "origin": ""
    },
    {
      "name": "Aiden Smalls",
      "jersey": "22",
      "class": "FR",
      "position_group": "Wide Receivers",
      "height_weight": "5'11\"/183",
      "snaps": null,
      "snap_pct": null,
      "rating": 0.87,
      "origin": ""
    },
    {
      "name": "Tyreek Copper",
      "jersey": "85",
      "class": "FR",
      "position_group": "Wide Receivers",
      "height_weight": "6'1\"/185",
      "snaps": null,
      "snap_pct": null,
      "rating": 0.85,
      "origin": ""
    },
    {
      "name": "Hunter Provience",
      "jersey": "86",
      "class": "JR",
      "position_group": "Tight Ends",
      "height_weight": "6'5\"/245",
      "snaps": 356,
      "snap_pct": 25.0,
      "rating": 0.89,
      "origin": ""
    },
    {
      "name": "Preston Douglas",
      "jersey": "19",
      "class": "SO",
      "position_group": "Tight Ends",
      "height_weight": "6'3\"/228",
      "snaps": 52,
      "snap_pct": 4.0,
      "rating": 0.86,
      "origin": ""
    },
    {
      "name": "Ian Flynt",
      "jersey": "43",
      "class": "SO",
      "position_group": "Tight Ends",
      "height_weight": "6'4\"/265",
      "snaps": 5,
      "snap_pct": 0.0,
      "rating": 0.84,
      "origin": ""
    },
    {
      "name": "Gus Ritchey",
      "jersey": "44",
      "class": "FR",
      "position_group": "Tight Ends",
      "height_weight": "6'2\"/235",
      "snaps": 1,
      "snap_pct": 0.0,
      "rating": 0.87,
      "origin": ""
    },
    {
      "name": "Tex Vaughn",
      "jersey": "45",
      "class": "FR",
      "position_group": "Tight Ends",
      "height_weight": "6'2\"/231",
      "snaps": null,
      "snap_pct": null,
      "rating": 0.89,
      "origin": ""
    },
    {
      "name": "Vander Ploog",
      "jersey": "88",
      "class": "FR",
      "position_group": "Tight Ends",
      "height_weight": "6'6\"/230",
      "snaps": null,
      "snap_pct": null,
      "rating": 0.87,
      "origin": ""
    },
    {
      "name": "Stephen Brown",
      "jersey": "00",
      "class": "FR",
      "position_group": "Tight Ends",
      "height_weight": "6'7\"/205",
      "snaps": null,
      "snap_pct": null,
      "rating": 0.85,
      "origin": ""
    },
    {
      "name": "Jimarion McCrimon",
      "jersey": "62",
      "class": "JR",
      "position_group": "Offensive Line",
      "height_weight": "6'5\"/295",
      "snaps": 866,
      "snap_pct": 89.1,
      "rating": 0.86,
      "origin": ""
    },
    {
      "name": "Teague Andersen",
      "jersey": "54",
      "class": "SR",
      "position_group": "Offensive Line",
      "height_weight": "6'5\"/322",
      "snaps": 727,
      "snap_pct": 83.0,
      "rating": 0.84,
      "origin": ""
    },
    {
      "name": "Jai'Lun Hampton",
      "jersey": "74",
      "class": "GR",
      "position_group": "Offensive Line",
      "height_weight": "6'8\"/345",
      "snaps": null,
      "snap_pct": null,
      "rating": 0.83,
      "origin": ""
    },
    {
      "name": "Brady Sakowitz",
      "jersey": "73",
      "class": "FR",
      "position_group": "Offensive Line",
      "height_weight": "6'6\"/328",
      "snaps": null,
      "snap_pct": null,
      "rating": 0.86,
      "origin": ""
    },
    {
      "name": "Tyler West",
      "jersey": "61",
      "class": "SO",
      "position_group": "Offensive Line",
      "height_weight": "6'5\"/291",
      "snaps": null,
      "snap_pct": null,
      "rating": 0.87,
      "origin": ""
    },
    {
      "name": "Brody Smith",
      "jersey": "56",
      "class": "FR",
      "position_group": "Offensive Line",
      "height_weight": "6'5\"/303",
      "snaps": null,
      "snap_pct": null,
      "rating": 0.87,
      "origin": ""
    },
    {
      "name": "Kamen Smith",
      "jersey": "79",
      "class": "JR",
      "position_group": "Offensive Line",
      "height_weight": "6'5\"/325",
      "snaps": 426,
      "snap_pct": 49.0,
      "rating": 0.87,
      "origin": ""
    },
    {
      "name": "Spike Sowells",
      "jersey": "72",
      "class": "SO",
      "position_group": "Offensive Line",
      "height_weight": "6'2\"/312",
      "snaps": 350,
      "snap_pct": 40.0,
      "rating": 0.93,
      "origin": ""
    },
    {
      "name": "Rico Jackson",
      "jersey": "64",
      "class": "JR",
      "position_group": "Offensive Line",
      "height_weight": "6'6\"/322",
      "snaps": 315,
      "snap_pct": 36.0,
      "rating": 0.84,
      "origin": ""
    },
    {
      "name": "Yousef Mugharbil",
      "jersey": "71",
      "class": "GR",
      "position_group": "Offensive Line",
      "height_weight": "6'5\"/322",
      "snaps": 114,
      "snap_pct": 13.0,
      "rating": 0.91,
      "origin": ""
    },
    {
      "name": "Rylan Vann",
      "jersey": "55",
      "class": "SR",
      "position_group": "Offensive Line",
      "height_weight": "6'1\"/285",
      "snaps": 23,
      "snap_pct": 3.0,
      "rating": 0.85,
      "origin": ""
    },
    {
      "name": "Daniel Cruz",
      "jersey": "50",
      "class": "SO",
      "position_group": "Offensive Line",
      "height_weight": "6'2\"/315",
      "snaps": 14,
      "snap_pct": 1.8,
      "rating": 0.86,
      "origin": ""
    },
    {
      "name": "TK Whitset",
      "jersey": "70",
      "class": "FR",
      "position_group": "Offensive Line",
      "height_weight": "6'4\"/300",
      "snaps": null,
      "snap_pct": null,
      "rating": 0.89,
      "origin": ""
    },
    {
      "name": "Michael Gibbs",
      "jersey": "76",
      "class": "FR",
      "position_group": "Offensive Line",
      "height_weight": "6'4\"/303",
      "snaps": null,
      "snap_pct": null,
      "rating": 0.88,
      "origin": ""
    },
    {
      "name": "Trent Mitchell",
      "jersey": "78",
      "class": "SO",
      "position_group": "Offensive Line",
      "height_weight": "6'5\"/316",
      "snaps": null,
      "snap_pct": null,
      "rating": 0.87,
      "origin": ""
    },
    {
      "name": "Tre Aiken",
      "jersey": "75",
      "class": "FR",
      "position_group": "Offensive Line",
      "height_weight": "6'3\"/310",
      "snaps": null,
      "snap_pct": null,
      "rating": 0.86,
      "origin": ""
    },
    {
      "name": "Kage Payne",
      "jersey": "52",
      "class": "FR",
      "position_group": "Offensive Line",
      "height_weight": "6'2\"/290",
      "snaps": null,
      "snap_pct": null,
      "rating": 0.85,
      "origin": ""
    },
    {
      "name": "Aiden Arias",
      "jersey": "92",
      "class": "JR",
      "position_group": "Offensive Line",
      "height_weight": "6'0\"/207",
      "snaps": null,
      "snap_pct": null,
      "rating": null,
      "origin": "NA"
    },
    {
      "name": "Chase Bond",
      "jersey": "92",
      "class": "SO",
      "position_group": "Defensive Line",
      "height_weight": "6'4\"/265",
      "snaps": 230,
      "snap_pct": 18.0,
      "rating": 0.85,
      "origin": ""
    },
    {
      "name": "Joseph Adedire",
      "jersey": "13",
      "class": "SR",
      "position_group": "Defensive Line",
      "height_weight": "6'3\"/260",
      "snaps": 95,
      "snap_pct": 8.0,
      "rating": 0.87,
      "origin": ""
    },
    {
      "name": "Jacquey Ferguson Jr",
      "jersey": "00",
      "class": "FR",
      "position_group": "Defensive Line",
      "height_weight": "6'3\"/236",
      "snaps": null,
      "snap_pct": null,
      "rating": 0.85,
      "origin": ""
    },
    {
      "name": "Isaiah Shirley",
      "jersey": "88",
      "class": "JR",
      "position_group": "Defensive Line",
      "height_weight": "6'3\"/280",
      "snaps": 344,
      "snap_pct": 42.0,
      "rating": 0.88,
      "origin": ""
    },
    {
      "name": "Katron Evans",
      "jersey": "55",
      "class": "GR",
      "position_group": "Defensive Line",
      "height_weight": "6'3\"/336",
      "snaps": 233,
      "snap_pct": 25.2,
      "rating": 0.86,
      "origin": ""
    },
    {
      "name": "Josiah Victor",
      "jersey": "90",
      "class": "SO",
      "position_group": "Defensive Line",
      "height_weight": "6'2\"/312",
      "snaps": 121,
      "snap_pct": 15.0,
      "rating": 0.85,
      "origin": ""
    },
    {
      "name": "Adrian Farrow",
      "jersey": "47",
      "class": "SO",
      "position_group": "Defensive Line",
      "height_weight": "6'3\"/265",
      "snaps": 17,
      "snap_pct": 2.0,
      "rating": 0.86,
      "origin": ""
    },
    {
      "name": "Omarian Abraham",
      "jersey": "56",
      "class": "FR",
      "position_group": "Defensive Line",
      "height_weight": "6'1\"/297",
      "snaps": 2,
      "snap_pct": 0.0,
      "rating": 0.86,
      "origin": ""
    },
    {
      "name": "Colby Cronk",
      "jersey": "34",
      "class": "FR",
      "position_group": "Defensive Line",
      "height_weight": "6'3\"/270",
      "snaps": null,
      "snap_pct": null,
      "rating": 0.88,
      "origin": ""
    },
    {
      "name": "Damaad Lewis",
      "jersey": "00",
      "class": "FR",
      "position_group": "Defensive Line",
      "height_weight": "6'4\"/245",
      "snaps": null,
      "snap_pct": null,
      "rating": 0.89,
      "origin": ""
    },
    {
      "name": "Carmelo McKenzie",
      "jersey": "93",
      "class": "FR",
      "position_group": "Defensive Line",
      "height_weight": "6'1\"/313",
      "snaps": null,
      "snap_pct": null,
      "rating": 0.85,
      "origin": ""
    },
    {
      "name": "Harvey Dyson",
      "jersey": "5",
      "class": "SR",
      "position_group": "Linebackers",
      "height_weight": "6'2\"/248",
      "snaps": 451,
      "snap_pct": 103.0,
      "rating": 0.86,
      "origin": ""
    },
    {
      "name": "Raul Aguirre Jr",
      "jersey": "10",
      "class": "SR",
      "position_group": "Linebackers",
      "height_weight": "6'2\"/233",
      "snaps": 304,
      "snap_pct": 70.0,
      "rating": 0.88,
      "origin": ""
    },
    {
      "name": "AJ Richardson",
      "jersey": "15",
      "class": "JR",
      "position_group": "Linebackers",
      "height_weight": "6'1\"/235",
      "snaps": 88,
      "snap_pct": 20.0,
      "rating": 0.85,
      "origin": ""
    },
    {
      "name": "Ke'Von Carter",
      "jersey": "42",
      "class": "SO",
      "position_group": "Linebackers",
      "height_weight": "6'3\"/223",
      "snaps": 73,
      "snap_pct": 17.0,
      "rating": 0.86,
      "origin": ""
    },
    {
      "name": "Zane Williams",
      "jersey": "30",
      "class": "SO",
      "position_group": "Linebackers",
      "height_weight": "5'11\"/228",
      "snaps": 44,
      "snap_pct": 10.0,
      "rating": 0.84,
      "origin": ""
    },
    {
      "name": "LaCorian Hodge",
      "jersey": "35",
      "class": "SO",
      "position_group": "Linebackers",
      "height_weight": "6'2\"/217",
      "snaps": 41,
      "snap_pct": 9.0,
      "rating": 0.87,
      "origin": ""
    },
    {
      "name": "Sterling Dixon",
      "jersey": "25",
      "class": "SO",
      "position_group": "Linebackers",
      "height_weight": "6'2\"/221",
      "snaps": 9,
      "snap_pct": 2.0,
      "rating": 0.87,
      "origin": ""
    },
    {
      "name": "DaKaari Nelson",
      "jersey": "8",
      "class": "JR",
      "position_group": "Linebackers",
      "height_weight": "6'3\"/234",
      "snaps": 2,
      "snap_pct": 0.0,
      "rating": 0.86,
      "origin": ""
    },
    {
      "name": "Logan Foust",
      "jersey": "38",
      "class": "SO",
      "position_group": "Linebackers",
      "height_weight": "6'0\"/205",
      "snaps": 1,
      "snap_pct": 0.0,
      "rating": null,
      "origin": "NA"
    },
    {
      "name": "Kevon Carter",
      "jersey": "42",
      "class": "SO",
      "position_group": "Linebackers",
      "height_weight": "6'3\"/210",
      "snaps": null,
      "snap_pct": null,
      "rating": 0.86,
      "origin": ""
    },
    {
      "name": "Caleb Gordon",
      "jersey": "32",
      "class": "FR",
      "position_group": "Linebackers",
      "height_weight": "5'11\"/226",
      "snaps": null,
      "snap_pct": null,
      "rating": 0.87,
      "origin": ""
    },
    {
      "name": "Elijah Satchell",
      "jersey": "58",
      "class": "FR",
      "position_group": "Linebackers",
      "height_weight": "6'3\"/229",
      "snaps": null,
      "snap_pct": null,
      "rating": 0.87,
      "origin": ""
    },
    {
      "name": "Ziggy Moore",
      "jersey": "33",
      "class": "FR",
      "position_group": "Linebackers",
      "height_weight": "6'2\"/210",
      "snaps": null,
      "snap_pct": null,
      "rating": 0.87,
      "origin": ""
    },
    {
      "name": "Jordan Moreta",
      "jersey": "44",
      "class": "FR",
      "position_group": "Linebackers",
      "height_weight": "6'1\"/223",
      "snaps": null,
      "snap_pct": null,
      "rating": 0.86,
      "origin": ""
    },
    {
      "name": "Bailey Benson",
      "jersey": "31",
      "class": "FR",
      "position_group": "Linebackers",
      "height_weight": "6'0\"/207",
      "snaps": null,
      "snap_pct": null,
      "rating": 0.85,
      "origin": ""
    },
    {
      "name": "Lawrence Brown Jr",
      "jersey": "37",
      "class": "FR",
      "position_group": "Linebackers",
      "height_weight": "6'3\"/209",
      "snaps": null,
      "snap_pct": null,
      "rating": 0.85,
      "origin": ""
    },
    {
      "name": "Brian Nelson II",
      "jersey": "7",
      "class": "JR",
      "position_group": "Linebackers",
      "height_weight": "6'0\"/197",
      "snaps": 637,
      "snap_pct": 51.0,
      "rating": 0.88,
      "origin": ""
    },
    {
      "name": "Jackson Vick",
      "jersey": "22",
      "class": "SR",
      "position_group": "Linebackers",
      "height_weight": "6'0\"/190",
      "snaps": 632,
      "snap_pct": 50.0,
      "rating": 0.86,
      "origin": ""
    },
    {
      "name": "Ty White",
      "jersey": "10",
      "class": "SO",
      "position_group": "Linebackers",
      "height_weight": "5'10\"/176",
      "snaps": 36,
      "snap_pct": 3.0,
      "rating": 0.85,
      "origin": ""
    },
    {
      "name": "Caden Gordon",
      "jersey": "12",
      "class": "SO",
      "position_group": "Linebackers",
      "height_weight": "6'1\"/194",
      "snaps": 35,
      "snap_pct": 3.0,
      "rating": 0.87,
      "origin": ""
    },
    {
      "name": "Michael Tate",
      "jersey": "24",
      "class": "JR",
      "position_group": "Linebackers",
      "height_weight": "6'2\"/180",
      "snaps": 27,
      "snap_pct": 2.0,
      "rating": null,
      "origin": "NA"
    },
    {
      "name": "DJ Dillard",
      "jersey": "38",
      "class": "SO",
      "position_group": "Linebackers",
      "height_weight": "5'8\"/165",
      "snaps": 1,
      "snap_pct": 0.0,
      "rating": null,
      "origin": "NA"
    },
    {
      "name": "Jordyn Best",
      "jersey": "26",
      "class": "FR",
      "position_group": "Linebackers",
      "height_weight": "5'10\"/171",
      "snaps": null,
      "snap_pct": null,
      "rating": 0.88,
      "origin": ""
    },
    {
      "name": "Jordan Jackson",
      "jersey": "30",
      "class": "FR",
      "position_group": "Linebackers",
      "height_weight": "5'11\"/165",
      "snaps": null,
      "snap_pct": null,
      "rating": 0.87,
      "origin": ""
    },
    {
      "name": "Jaren Sensabaugh",
      "jersey": "14",
      "class": "SO",
      "position_group": "Linebackers",
      "height_weight": "6'1\"/190",
      "snaps": null,
      "snap_pct": null,
      "rating": 0.87,
      "origin": ""
    },
    {
      "name": "Cam Strong",
      "jersey": "27",
      "class": "FR",
      "position_group": "Linebackers",
      "height_weight": "6'0\"/183",
      "snaps": null,
      "snap_pct": null,
      "rating": 0.87,
      "origin": ""
    },
    {
      "name": "Gerritt Kemp",
      "jersey": "21",
      "class": "FR",
      "position_group": "Linebackers",
      "height_weight": "6'2\"/187",
      "snaps": null,
      "snap_pct": null,
      "rating": 0.87,
      "origin": ""
    },
    {
      "name": "Asaad Brown Jr",
      "jersey": "6",
      "class": "SO",
      "position_group": "Linebackers",
      "height_weight": "6'0\"/199",
      "snaps": 673,
      "snap_pct": 54.0,
      "rating": 0.88,
      "origin": ""
    },
    {
      "name": "King Mack",
      "jersey": "16",
      "class": "SR",
      "position_group": "Linebackers",
      "height_weight": "5'10\"/184",
      "snaps": 493,
      "snap_pct": 40.0,
      "rating": 0.87,
      "origin": ""
    },
    {
      "name": "Ronnie Royal III",
      "jersey": "2",
      "class": "SO",
      "position_group": "Linebackers",
      "height_weight": "5'9\"/185",
      "snaps": 442,
      "snap_pct": 36.0,
      "rating": 0.89,
      "origin": ""
    },
    {
      "name": "Tristan Teasdell",
      "jersey": "3",
      "class": "SO",
      "position_group": "Linebackers",
      "height_weight": "5'11\"/180",
      "snaps": 369,
      "snap_pct": 30.0,
      "rating": 0.86,
      "origin": ""
    },
    {
      "name": "Brody Barnhardt",
      "jersey": "29",
      "class": "SO",
      "position_group": "Linebackers",
      "height_weight": "6'0\"/190",
      "snaps": 209,
      "snap_pct": 17.0,
      "rating": 0.87,
      "origin": ""
    },
    {
      "name": "Koby Sarkodie",
      "jersey": "00",
      "class": "FR",
      "position_group": "Linebackers",
      "height_weight": "6'3\"/206",
      "snaps": null,
      "snap_pct": null,
      "rating": 0.88,
      "origin": ""
    },
    {
      "name": "D'Various Surratt",
      "jersey": "00",
      "class": "FR",
      "position_group": "Linebackers",
      "height_weight": "6'0\"/185",
      "snaps": null,
      "snap_pct": null,
      "rating": 0.88,
      "origin": ""
    },
    {
      "name": "Tristen Hill",
      "jersey": "36",
      "class": "FR",
      "position_group": "Linebackers",
      "height_weight": "5'10\"/192",
      "snaps": null,
      "snap_pct": null,
      "rating": 0.87,
      "origin": ""
    },
    {
      "name": "Chino Aguirre",
      "jersey": "28",
      "class": "FR",
      "position_group": "Linebackers",
      "height_weight": "6'0\"/205",
      "snaps": null,
      "snap_pct": null,
      "rating": 0.87,
      "origin": ""
    },
    {
      "name": "Isaiah Crowell",
      "jersey": "8",
      "class": "GR",
      "position_group": "Linebackers",
      "height_weight": "5'11\"/185",
      "snaps": null,
      "snap_pct": null,
      "rating": 0.87,
      "origin": ""
    },
    {
      "name": "Ondre Evans",
      "jersey": "20",
      "class": "SO",
      "position_group": "Linebackers",
      "height_weight": "6'0\"/187",
      "snaps": null,
      "snap_pct": null,
      "rating": 0.87,
      "origin": ""
    },
    {
      "name": "Kanoah Vinesett",
      "jersey": "94",
      "class": "GR",
      "position_group": "Kickers",
      "height_weight": "6'1\"/205",
      "snaps": 6,
      "snap_pct": 83.3,
      "rating": null,
      "origin": "NA"
    },
    {
      "name": "Nick Konieczynski",
      "jersey": "91",
      "class": "SO",
      "position_group": "Kickers",
      "height_weight": "5'11\"/215",
      "snaps": 3,
      "snap_pct": 33.3,
      "rating": null,
      "origin": "NA"
    },
    {
      "name": "Jackson Waller",
      "jersey": "96",
      "class": "SO",
      "position_group": "Punters",
      "height_weight": "6'2\"/214",
      "snaps": null,
      "snap_pct": null,
      "rating": 0.74,
      "origin": ""
    },
    {
      "name": "Cristian Harthan",
      "jersey": "97",
      "class": "FR",
      "position_group": "Punters",
      "height_weight": "6'5\"/195",
      "snaps": null,
      "snap_pct": null,
      "rating": 0.82,
      "origin": ""
    }
  ],
  "portal_in": [
    {
      "name": "Hunter Provience",
      "position": "TE",
      "school": "Montana State",
      "stars": 3,
      "rating": 89,
      "date": "01-10-26"
    },
    {
      "name": "Raul Aguirre Jr.",
      "position": "LB",
      "school": "Miami",
      "stars": 3,
      "rating": 88,
      "date": "01-25-26"
    },
    {
      "name": "Joshisa Trader",
      "position": "WR",
      "school": "Miami",
      "stars": 3,
      "rating": 88,
      "date": "01-22-26"
    },
    {
      "name": "Vander Ploog",
      "position": "TE",
      "school": "Oregon",
      "stars": 3,
      "rating": 87,
      "date": "01-20-26"
    },
    {
      "name": "King Mack",
      "position": "S",
      "school": "Penn State",
      "stars": 3,
      "rating": 87,
      "date": "01-08-26"
    },
    {
      "name": "Ondre Evans",
      "position": "CB",
      "school": "Georgia",
      "stars": 3,
      "rating": 87,
      "date": "01-08-26"
    },
    {
      "name": "Tyran Warren",
      "position": "WR",
      "school": "Alcorn State",
      "stars": 3,
      "rating": 86,
      "date": "01-11-26"
    },
    {
      "name": "Davion Gause",
      "position": "RB",
      "school": "North Carolina",
      "stars": 3,
      "rating": 86,
      "date": "01-10-26"
    },
    {
      "name": "Harvey Dyson",
      "position": "EDGE",
      "school": "Tulane",
      "stars": 3,
      "rating": 86,
      "date": "01-10-26"
    },
    {
      "name": "Daniel Cruz",
      "position": "IOL",
      "school": "Texas",
      "stars": 3,
      "rating": 86,
      "date": "01-12-26"
    },
    {
      "name": "DaKaari Nelson",
      "position": "LB",
      "school": "Penn State",
      "stars": 3,
      "rating": 86,
      "date": "01-16-26"
    },
    {
      "name": "KaTron Evans",
      "position": "DL",
      "school": "Marshall",
      "stars": 3,
      "rating": 86,
      "date": "01-16-26"
    },
    {
      "name": "Chance Robinson",
      "position": "WR",
      "school": "Miami",
      "stars": 3,
      "rating": 86,
      "date": "01-09-26"
    },
    {
      "name": "Victor Snow",
      "position": "WR",
      "school": "Buffalo",
      "stars": 3,
      "rating": 86,
      "date": "01-05-26"
    },
    {
      "name": "Jimarion McCrimon",
      "position": "OT",
      "school": "East Carolina",
      "stars": 3,
      "rating": 86,
      "date": "01-05-26"
    },
    {
      "name": "Ty White",
      "position": "CB",
      "school": "North Carolina",
      "stars": 3,
      "rating": 85,
      "date": "01-13-26"
    },
    {
      "name": "Davion Dozier",
      "position": "WR",
      "school": "App State",
      "stars": 3,
      "rating": 85,
      "date": "01-17-26"
    },
    {
      "name": "Jackson Waller",
      "position": "P",
      "school": "SMU",
      "stars": 0,
      "rating": 0,
      "date": "01-06-26"
    },
    {
      "name": "Tad Hudson",
      "position": "QB",
      "school": "Coastal Carolina",
      "stars": 4,
      "rating": 0,
      "date": "02-15-26"
    },
    {
      "name": "Jai'Lun Hampton",
      "position": "OT",
      "school": "UT Martin",
      "stars": 3,
      "rating": 0,
      "date": "02-16-26"
    }
  ],
  "portal_out": [
    {
      "name": "Terrell Anderson",
      "position": "WR",
      "school": "USC",
      "stars": 4,
      "rating": 94,
      "date": "01-05-26"
    },
    {
      "name": "Jacarrius Peak",
      "position": "OT",
      "school": "South Carolina",
      "stars": 4,
      "rating": 94,
      "date": "01-08-26"
    },
    {
      "name": "Hollywood Smothers",
      "position": "RB",
      "school": "Texas",
      "stars": 4,
      "rating": 94,
      "date": "01-11-26"
    },
    {
      "name": "Noah Rogers",
      "position": "WR",
      "school": "Alabama",
      "stars": 4,
      "rating": 90,
      "date": "01-12-26"
    },
    {
      "name": "Elijah Groves",
      "position": "LB",
      "school": "Sam Houston",
      "stars": 3,
      "rating": 86,
      "date": "01-10-26"
    },
    {
      "name": "Joshua Ofor",
      "position": "LB",
      "school": "Arkansas State",
      "stars": 3,
      "rating": 86,
      "date": "01-18-26"
    },
    {
      "name": "Kenny Soares Jr.",
      "position": "LB",
      "school": "Michigan State",
      "stars": 3,
      "rating": 86,
      "date": "01-13-26"
    },
    {
      "name": "Tank Boston",
      "position": "WR",
      "school": "Charlotte",
      "stars": 3,
      "rating": 85,
      "date": "01-12-26"
    },
    {
      "name": "Jivan Baly",
      "position": "CB",
      "school": "Old Dominion",
      "stars": 3,
      "rating": 85,
      "date": "01-18-26"
    },
    {
      "name": "Justin Terrell",
      "position": "DL",
      "school": "Sam Houston",
      "stars": 3,
      "rating": 85,
      "date": "01-10-26"
    },
    {
      "name": "Rente Hinton",
      "position": "S",
      "school": "Marshall",
      "stars": 3,
      "rating": 84,
      "date": "01-13-26"
    },
    {
      "name": "Darion Rivers",
      "position": "OT",
      "school": "Troy",
      "stars": 3,
      "rating": 83,
      "date": "01-17-26"
    },
    {
      "name": "Terris Dudley",
      "position": "LB",
      "school": "UConn",
      "stars": 3,
      "rating": 0,
      "date": "01-11-26"
    },
    {
      "name": "Brock Stukes",
      "position": "IOL",
      "school": "Sam Houston",
      "stars": 0,
      "rating": 0,
      "date": "01-12-26"
    },
    {
      "name": "Zack Myers",
      "position": "S",
      "school": "TBD",
      "stars": 4,
      "rating": 0,
      "date": "01-02-26"
    },
    {
      "name": "Val Erickson",
      "position": "OT",
      "school": "Liberty",
      "stars": 3,
      "rating": 0,
      "date": "01-04-26"
    },
    {
      "name": "Daemon Fagan",
      "position": "S",
      "school": "TBD",
      "stars": 4,
      "rating": 0,
      "date": "01-02-26"
    },
    {
      "name": "Kelvon McBride",
      "position": "LB",
      "school": "Marshall",
      "stars": 3,
      "rating": 0,
      "date": "01-06-26"
    },
    {
      "name": "Odera Orizu",
      "position": "EDGE",
      "school": "UConn",
      "stars": 0,
      "rating": 0,
      "date": "01-24-26"
    },
    {
      "name": "Lex Thomas",
      "position": "QB",
      "school": "TBD",
      "stars": 3,
      "rating": 0,
      "date": "01-10-26"
    },
    {
      "name": "Christian Zachary",
      "position": "WR",
      "school": "Sam Houston",
      "stars": 3,
      "rating": 0,
      "date": "02-02-26"
    },
    {
      "name": "Josh Alexander-Felton",
      "position": "DL",
      "school": "TBD",
      "stars": 3,
      "rating": 0,
      "date": "12-12-25"
    }
  ],
  "portal_net": -2,
  "recruiting_class_2026": [
    {
      "name": "Damaad Lewis",
      "position": "DL",
      "stars": 3,
      "rating": 89.0,
      "ranking": 463,
      "height_weight": "6' 4/245",
      "location": "Charlotte, NC"
    },
    {
      "name": "Amiri Acker",
      "position": "WR",
      "stars": 3,
      "rating": 88.33,
      "ranking": 603,
      "height_weight": "6' 2/186",
      "location": "Iva, SC"
    },
    {
      "name": "Jordyn Best",
      "position": "CB",
      "stars": 3,
      "rating": 88.0,
      "ranking": 680,
      "height_weight": "5' 11/180",
      "location": "Columbia, SC"
    },
    {
      "name": "D'Various Surratt",
      "position": "S",
      "stars": 3,
      "rating": 87.67,
      "ranking": 774,
      "height_weight": "6' 0/185",
      "location": "Shelby, NC"
    },
    {
      "name": "Koby Sarkodie",
      "position": "S",
      "stars": 3,
      "rating": 87.56,
      "ranking": 831,
      "height_weight": "6' 3/206",
      "location": "Gwynn Oak, MD"
    },
    {
      "name": "Ziggy Moore",
      "position": "LB",
      "stars": 3,
      "rating": 87.44,
      "ranking": 866,
      "height_weight": "6' 2/218",
      "location": "Pittsburgh, PA"
    },
    {
      "name": "Tristen Hill",
      "position": "S",
      "stars": 3,
      "rating": 87.33,
      "ranking": 907,
      "height_weight": "5' 10/190",
      "location": "Suwanee, GA"
    },
    {
      "name": "Chino Aguirre",
      "position": "S",
      "stars": 3,
      "rating": 87.33,
      "ranking": 907,
      "height_weight": "6' 0/185",
      "location": "Locust Grove, GA"
    },
    {
      "name": "Aiden Smalls",
      "position": "ATH",
      "stars": 3,
      "rating": 87.11,
      "ranking": 1009,
      "height_weight": "6' 1/175",
      "location": "Clayton, NC"
    },
    {
      "name": "Jai Richburg",
      "position": "WR",
      "stars": 3,
      "rating": 87.11,
      "ranking": 1009,
      "height_weight": "6' 3/180",
      "location": "Kernersville, NC"
    },
    {
      "name": "Caleb Gordon",
      "position": "LB",
      "stars": 3,
      "rating": 86.67,
      "ranking": 1227,
      "height_weight": "6' 0/215",
      "location": "Gastonia, NC"
    },
    {
      "name": "Jordan Jackson",
      "position": "CB",
      "stars": 3,
      "rating": 86.67,
      "ranking": 1227,
      "height_weight": "6' 1/165",
      "location": "Winter Park, FL"
    },
    {
      "name": "Elijah Satchell",
      "position": "DL",
      "stars": 3,
      "rating": 86.67,
      "ranking": 1227,
      "height_weight": "6' 2/230",
      "location": "Camden, NJ"
    },
    {
      "name": "Brody Smith",
      "position": "OT",
      "stars": 3,
      "rating": 86.5,
      "ranking": 1296,
      "height_weight": "6' 6/315",
      "location": "Maryville, TN"
    },
    {
      "name": "Dylan McCoy",
      "position": "RB",
      "stars": 3,
      "rating": 86.44,
      "ranking": 1320,
      "height_weight": "5' 11/185",
      "location": "Buford, GA"
    },
    {
      "name": "Tre Aiken",
      "position": "OT",
      "stars": 3,
      "rating": 86.22,
      "ranking": 1422,
      "height_weight": "6' 3/286",
      "location": "Clinton, SC"
    },
    {
      "name": "Noah Moss",
      "position": "RB",
      "stars": 3,
      "rating": 86.22,
      "ranking": 1422,
      "height_weight": "6' 1/205",
      "location": "Fairhope, AL"
    },
    {
      "name": "Jordan Moreta",
      "position": "LB",
      "stars": 3,
      "rating": 85.83,
      "ranking": 1392,
      "height_weight": "6' 2/215",
      "location": "Paramus, NJ"
    },
    {
      "name": "Brady Sakowitz",
      "position": "OT",
      "stars": 3,
      "rating": 85.78,
      "ranking": 1656,
      "height_weight": "6' 6/295",
      "location": "Richmond, VA"
    },
    {
      "name": "Stephen Brown",
      "position": "TE",
      "stars": 3,
      "rating": 85.44,
      "ranking": 1816,
      "height_weight": "6' 7/205",
      "location": "Chicago, IL"
    },
    {
      "name": "Carmelo McKenzie",
      "position": "DL",
      "stars": 3,
      "rating": 85.19,
      "ranking": 1539,
      "height_weight": "6' 2/280",
      "location": "Bradenton, FL"
    },
    {
      "name": "Jacquey Ferguson Jr.",
      "position": "EDGE",
      "stars": 3,
      "rating": 85.11,
      "ranking": 1903,
      "height_weight": "6' 3/236",
      "location": "St. Petersburg, FL"
    },
    {
      "name": "Tyreek Copper",
      "position": "WR",
      "stars": 3,
      "rating": 85.0,
      "ranking": 1589,
      "height_weight": "6' 2/180",
      "location": "Kinston, NC"
    },
    {
      "name": "Jacob Smith",
      "position": "QB",
      "stars": 3,
      "rating": 84.89,
      "ranking": 2116,
      "height_weight": "6' 1/205",
      "location": "Pfafftown, NC"
    },
    {
      "name": "Lawrence Brown",
      "position": "EDGE",
      "stars": 3,
      "rating": 84.67,
      "ranking": 2145,
      "height_weight": "6' 3/200",
      "location": "Loganville, GA"
    }
  ],
  "schedule_2026": [
    {
      "week": 1,
      "date": "Sat, 8/29",
      "location": "vs*",
      "opponent": "Virginia Cavaliers",
      "opp_record": "0-0",
      "opp_rank": 32,
      "off_rank": 45,
      "def_rank": 28,
      "favorite": "Virginia",
      "line": 3.5,
      "win_pct": null,
      "proj_w": null,
      "proj_l": null,
      "conference_game": true
    },
    {
      "week": 2,
      "date": "Sat, 9/12",
      "location": "vs",
      "opponent": "Richmond Spiders",
      "opp_record": "0-0",
      "opp_rank": 136,
      "off_rank": 136,
      "def_rank": 136,
      "favorite": "NC State",
      "line": -28.5,
      "win_pct": 99,
      "proj_w": 1.5,
      "proj_l": 0.5,
      "conference_game": false
    },
    {
      "week": 3,
      "date": "Sat, 9/19",
      "location": "at",
      "opponent": "Vanderbilt Commodores",
      "opp_record": "0-0",
      "opp_rank": 48,
      "off_rank": 56,
      "def_rank": 42,
      "favorite": "Vanderbilt",
      "line": 1.0,
      "win_pct": 52,
      "proj_w": 2.0,
      "proj_l": 1.0,
      "conference_game": false
    },
    {
      "week": 4,
      "date": "Sat, 9/26",
      "location": "vs",
      "opponent": "App State Mountaineers",
      "opp_record": "0-0",
      "opp_rank": 113,
      "off_rank": 117,
      "def_rank": 107,
      "favorite": "NC State",
      "line": -19.0,
      "win_pct": 91,
      "proj_w": 2.9,
      "proj_l": 1.1,
      "conference_game": false
    },
    {
      "week": 5,
      "date": "Sat, 10/3",
      "location": "vs",
      "opponent": "Louisville Cardinals",
      "opp_record": "0-0",
      "opp_rank": 22,
      "off_rank": 18,
      "def_rank": 30,
      "favorite": "Louisville",
      "line": 2.5,
      "win_pct": 45,
      "proj_w": 3.4,
      "proj_l": 1.6,
      "conference_game": true
    },
    {
      "week": 6,
      "date": "Sat, 10/10",
      "location": "vs",
      "opponent": "Wake Forest Demon Deacons",
      "opp_record": "0-0",
      "opp_rank": 43,
      "off_rank": 57,
      "def_rank": 36,
      "favorite": "NC State",
      "line": -4.0,
      "win_pct": 62,
      "proj_w": 4.0,
      "proj_l": 2.0,
      "conference_game": true
    },
    {
      "week": 8,
      "date": "Fri, 10/23",
      "location": "at",
      "opponent": "Stanford Cardinal",
      "opp_record": "0-0",
      "opp_rank": 97,
      "off_rank": 107,
      "def_rank": 68,
      "favorite": "NC State",
      "line": -8.5,
      "win_pct": 71,
      "proj_w": 4.7,
      "proj_l": 2.3,
      "conference_game": true
    },
    {
      "week": 9,
      "date": "Fri, 10/30",
      "location": "vs",
      "opponent": "California Golden Bears",
      "opp_record": "0-0",
      "opp_rank": 42,
      "off_rank": 28,
      "def_rank": 57,
      "favorite": "NC State",
      "line": -4.0,
      "win_pct": 62,
      "proj_w": 5.3,
      "proj_l": 2.7,
      "conference_game": true
    },
    {
      "week": 10,
      "date": "Fri, 11/6",
      "location": "vs",
      "opponent": "Duke Blue Devils",
      "opp_record": "0-0",
      "opp_rank": 53,
      "off_rank": 72,
      "def_rank": 38,
      "favorite": "NC State",
      "line": -4.5,
      "win_pct": 64,
      "proj_w": 5.9,
      "proj_l": 3.1,
      "conference_game": true
    },
    {
      "week": 11,
      "date": "Sat, 11/14",
      "location": "vs",
      "opponent": "Syracuse Orange",
      "opp_record": "0-0",
      "opp_rank": 87,
      "off_rank": 65,
      "def_rank": 105,
      "favorite": "NC State",
      "line": -10.5,
      "win_pct": 76,
      "proj_w": 6.7,
      "proj_l": 3.3,
      "conference_game": true
    },
    {
      "week": 12,
      "date": "Sat, 11/21",
      "location": "at",
      "opponent": "Florida State Seminoles",
      "opp_record": "0-0",
      "opp_rank": 33,
      "off_rank": 55,
      "def_rank": 24,
      "favorite": "Florida State",
      "line": 2.5,
      "win_pct": 45,
      "proj_w": 7.2,
      "proj_l": 3.8,
      "conference_game": true
    },
    {
      "week": 13,
      "date": "Sat, 11/28",
      "location": "at",
      "opponent": "North Carolina Tar Heels",
      "opp_record": "0-0",
      "opp_rank": 76,
      "off_rank": 71,
      "def_rank": 77,
      "favorite": "NC State",
      "line": -4.0,
      "win_pct": 62,
      "proj_w": 7.8,
      "proj_l": 4.2,
      "conference_game": true
    }
  ],
  "schedule_summary": {
    "total_opp_power": "12",
    "sos_rank": "73",
    "expected_record": null,
    "expected_conf_record": null,
    "p4_g6_opponents": "10 / 1\n",
    "vs_bowl_teams": "0 – 0\n"
  },
  "power_rating_value": 6.47,
  "offense_rating": 18.21,
  "defense_rating": 11.74,
  "power_rank_db": 35,
  "composite_rank": 70,
  "gc_net_raw": 4.31,
  "mc_net_raw": -1.15,
  "composite_score": 56.59,
  "offense_ppa_rank": 20,
  "defense_ppa_rank": 102,
  "offense_success_rank": 50,
  "defense_success_rank": 39,
  "offense_explosiveness_rank": 13,
  "defense_explosiveness_rank": 134,
  "offense_havoc_rank": 74,
  "defense_havoc_rank": 86,
  "offense_ppo_rank": 8,
  "defense_ppo_rank": 72,
  "offense_profile_db": "Balanced (50% pass, 50% run)",
  "scoring_home_ppg": 35.3,
  "scoring_home_games": 7,
  "scoring_road_ppg": 23.0,
  "scoring_road_games": 5,
  "best_players": [
    {
      "player_name": "Jayden Scott",
      "position": "RB",
      "points": 81,
      "statsline": "595 Yds, 4 TD"
    },
    {
      "player_name": "King Mack",
      "position": "S",
      "points": 79,
      "statsline": "1 Int, 3 Pd (* TR)"
    },
    {
      "player_name": "Victor Snow",
      "position": "WR",
      "points": 78,
      "statsline": "815 Yds, 8 TD (* TR)"
    },
    {
      "player_name": "Asaad Brown Jr.",
      "position": "S",
      "points": 71,
      "statsline": "1 Int, 2 Pd"
    },
    {
      "player_name": "CJ Bailey",
      "position": "QB",
      "points": 70,
      "statsline": "3105 Yds, 25 TD"
    },
    {
      "player_name": "Brian Nelson II",
      "position": "CB",
      "points": 68,
      "statsline": "0 Int, 6 Pd"
    },
    {
      "player_name": "Teague Andersen",
      "position": "T",
      "points": 68,
      "statsline": "C+ Block Grade"
    },
    {
      "player_name": "Jackson Waller",
      "position": "P",
      "points": 66,
      "statsline": "59 Punts, 41.3 YPP (* TR)"
    }
  ],
  "previous_head_coach": "Dave Doeren",
  "previous_oc": "Kurt Roper",
  "previous_dc": "D. J. Eliot",
  "db_enriched_at": "2026-04-05"
}